[
    {
        "commission": {
            "Nr komisji": "18",
            "Gmina": "gm. Złocieniec",
            "Teryt Gminy": "320306",
            "Powiat": "drawski",
            "Teryt Powiatu": "320300",
            "Województwo": "zachodniopomorskie",
            "Siedziba": "Samodzielny Publiczny Zakład Opieki Zdrowotnej Szpital Specjalistyczny MSWiA, ul. Kańsko 1, 78-520 Złocieniec",
            "Typ obwodu": "zakład leczniczy",
            "Typ obszaru": "miasto",
            "id": "f7a04b67690456941d1f937ee0b123fa"
        },
        "turnout": {
            "first": "100% (99 z 99)",
            "second": "100% (97 z 97)",
            "scale": 1
        },
        "first_round": {
            "eligible_voters_1": 99,
            "issued_1": 99,
            "turnout_1": 100,
            "BARTOSZEWICZ Artur_1": 1,
            "BIEJAT Magdalena Agnieszka_1": 2,
            "BRAUN Grzegorz Michał_1": 5,
            "HOŁOWNIA Szymon Franciszek_1": 5,
            "JAKUBIAK Marek_1": 2,
            "MACIAK Maciej_1": 0,
            "MENTZEN Sławomir Jerzy_1": 10,
            "NAWROCKI Karol Tadeusz_1": 31,
            "SENYSZYN Joanna_1": 1,
            "STANOWSKI Krzysztof Jakub_1": 0,
            "TRZASKOWSKI Rafał Kazimierz_1": 40,
            "WOCH Marek Marian_1": 0,
            "ZANDBERG Adrian Tadeusz_1": 2
        },
        "second_round": {
            "eligible_voters_2": 97,
            "issued_2": 97,
            "turnout_2": 100,
            "NAWROCKI Karol Tadeusz_2": 51,
            "TRZASKOWSKI Rafał Kazimierz_2": 45
        },
        "calculations": {
            "issued_scale": 0.9797979797979798,
            "change_TRZASKOWSKI Rafał Kazimierz": 0.125,
            "change_NAWROCKI Karol Tadeusz": 0.6452,
            "expected_nawrocki": 45.09,
            "expected_trzaskowski": 48.97,
            "delta_nawrocki": 5.912636363636359,
            "delta_trzaskowski": -3.9732424242424216,
            "diff_pct_nawrocki": 0.1311,
            "delta_from_median_change": -0.1736,
            "delta_from_median_difference": 0.1269,
            "alert_index": 0.1311,
            "change_TRZASKOWSKI Rafał Kazimierz_pct": 12.5,
            "change_NAWROCKI Karol Tadeusz_pct": 64.52,
            "diff_pct_nawrocki_pct": 13.11,
            "delta_from_median_change_pct": -17.36,
            "delta_from_median_difference_pct": 12.69,
            "alert_index_pct": 13.11
        },
        "alert_index_pct": 0.1311,
        "alert_index": 0.1311
    },
    {
        "commission": {
            "Nr komisji": "480",
            "Gmina": "zagranica",
            "Teryt Gminy": "",
            "Powiat": "",
            "Teryt Powiatu": "",
            "Województwo": "",
            "Siedziba": "Leicester, Polski Ośrodek przy Polskim Kościele Św. Pawła, Falmouth Road, LE5 4WH Leicester, Leicester, Zjednoczone Królestwo Wielkiej Brytanii i Irlandii Północnej",
            "Typ obwodu": "zagranica",
            "Typ obszaru": "zagranica",
            "id": "0ea996590fa4b2560620de07ac8b8527"
        },
        "turnout": {
            "first": "89.04% (1983 z 2227)",
            "second": "81.65% (2274 z 2785)",
            "scale": 0.9170035938903863
        },
        "first_round": {
            "eligible_voters_1": 2227,
            "issued_1": 1983,
            "turnout_1": 89.04,
            "BARTOSZEWICZ Artur_1": 7,
            "BIEJAT Magdalena Agnieszka_1": 97,
            "BRAUN Grzegorz Michał_1": 318,
            "HOŁOWNIA Szymon Franciszek_1": 65,
            "JAKUBIAK Marek_1": 12,
            "MACIAK Maciej_1": 5,
            "MENTZEN Sławomir Jerzy_1": 525,
            "NAWROCKI Karol Tadeusz_1": 251,
            "SENYSZYN Joanna_1": 16,
            "STANOWSKI Krzysztof Jakub_1": 31,
            "TRZASKOWSKI Rafał Kazimierz_1": 536,
            "WOCH Marek Marian_1": 2,
            "ZANDBERG Adrian Tadeusz_1": 99
        },
        "second_round": {
            "eligible_voters_2": 2785,
            "issued_2": 2274,
            "turnout_2": 81.65,
            "NAWROCKI Karol Tadeusz_2": 1061,
            "TRZASKOWSKI Rafał Kazimierz_2": 1186
        },
        "calculations": {
            "issued_scale": 1.146747352496218,
            "change_TRZASKOWSKI Rafał Kazimierz": 1.2127,
            "change_NAWROCKI Karol Tadeusz": 3.2271,
            "expected_nawrocki": 1220.93,
            "expected_trzaskowski": 1001.47,
            "delta_nawrocki": -159.92814523449306,
            "delta_trzaskowski": 184.5317760968229,
            "diff_pct_nawrocki": -0.131,
            "delta_from_median_change": 2.4083,
            "delta_from_median_difference": -0.1352,
            "alert_index": 0.131,
            "change_TRZASKOWSKI Rafał Kazimierz_pct": 121.27,
            "change_NAWROCKI Karol Tadeusz_pct": 322.71,
            "diff_pct_nawrocki_pct": -13.1,
            "delta_from_median_change_pct": 240.83,
            "delta_from_median_difference_pct": -13.52,
            "alert_index_pct": 13.1
        },
        "alert_index_pct": 0.131,
        "alert_index": 0.131
    },
    {
        "commission": {
            "Nr komisji": "22",
            "Gmina": "gm. Człuchów",
            "Teryt Gminy": "220303",
            "Powiat": "człuchowski",
            "Teryt Powiatu": "220300",
            "Województwo": "pomorskie",
            "Siedziba": "Świetlica Wiejska, Krępsk 26, 77-300 Człuchów",
            "Typ obwodu": "stały",
            "Typ obszaru": "wieś",
            "id": "2a0ed7c313f9e176ed696955c268cafa"
        },
        "turnout": {
            "first": "42.21% (122 z 289)",
            "second": "45.61% (130 z 285)",
            "scale": 1.0805496327884387
        },
        "first_round": {
            "eligible_voters_1": 289,
            "issued_1": 122,
            "turnout_1": 42.21,
            "BARTOSZEWICZ Artur_1": 1,
            "BIEJAT Magdalena Agnieszka_1": 2,
            "BRAUN Grzegorz Michał_1": 21,
            "HOŁOWNIA Szymon Franciszek_1": 2,
            "JAKUBIAK Marek_1": 1,
            "MACIAK Maciej_1": 2,
            "MENTZEN Sławomir Jerzy_1": 20,
            "NAWROCKI Karol Tadeusz_1": 54,
            "SENYSZYN Joanna_1": 1,
            "STANOWSKI Krzysztof Jakub_1": 0,
            "TRZASKOWSKI Rafał Kazimierz_1": 12,
            "WOCH Marek Marian_1": 0,
            "ZANDBERG Adrian Tadeusz_1": 4
        },
        "second_round": {
            "eligible_voters_2": 285,
            "issued_2": 130,
            "turnout_2": 45.61,
            "NAWROCKI Karol Tadeusz_2": 111,
            "TRZASKOWSKI Rafał Kazimierz_2": 19
        },
        "calculations": {
            "issued_scale": 1.0655737704918034,
            "change_TRZASKOWSKI Rafał Kazimierz": 0.5833,
            "change_NAWROCKI Karol Tadeusz": 1.0556,
            "expected_nawrocki": 98.14,
            "expected_trzaskowski": 25.47,
            "delta_nawrocki": 12.864918032786875,
            "delta_trzaskowski": -6.471475409836064,
            "diff_pct_nawrocki": 0.1311,
            "delta_from_median_change": 0.2368,
            "delta_from_median_difference": 0.1269,
            "alert_index": 0.131,
            "change_TRZASKOWSKI Rafał Kazimierz_pct": 58.33,
            "change_NAWROCKI Karol Tadeusz_pct": 105.56,
            "diff_pct_nawrocki_pct": 13.11,
            "delta_from_median_change_pct": 23.68,
            "delta_from_median_difference_pct": 12.69,
            "alert_index_pct": 13.1
        },
        "alert_index_pct": 0.131,
        "alert_index": 0.131
    },
    {
        "commission": {
            "Nr komisji": "79",
            "Gmina": "m. Gdynia",
            "Teryt Gminy": "226201",
            "Powiat": "Gdynia",
            "Teryt Powiatu": "226200",
            "Województwo": "pomorskie",
            "Siedziba": "III Liceum Ogólnokształcące z Oddziałami Dwujęzycznymi, ul. Legionów 27, 81-405 Gdynia",
            "Typ obwodu": "stały",
            "Typ obszaru": "miasto",
            "id": "ebb96f3a5ff88e385817f1798c5752e4"
        },
        "turnout": {
            "first": "73.44% (954 z 1299)",
            "second": "77.34% (1007 z 1302)",
            "scale": 1.0531045751633987
        },
        "first_round": {
            "eligible_voters_1": 1299,
            "issued_1": 954,
            "turnout_1": 73.44,
            "BARTOSZEWICZ Artur_1": 1,
            "BIEJAT Magdalena Agnieszka_1": 58,
            "BRAUN Grzegorz Michał_1": 29,
            "HOŁOWNIA Szymon Franciszek_1": 61,
            "JAKUBIAK Marek_1": 5,
            "MACIAK Maciej_1": 0,
            "MENTZEN Sławomir Jerzy_1": 84,
            "NAWROCKI Karol Tadeusz_1": 146,
            "SENYSZYN Joanna_1": 24,
            "STANOWSKI Krzysztof Jakub_1": 7,
            "TRZASKOWSKI Rafał Kazimierz_1": 445,
            "WOCH Marek Marian_1": 1,
            "ZANDBERG Adrian Tadeusz_1": 88
        },
        "second_round": {
            "eligible_voters_2": 1302,
            "issued_2": 1007,
            "turnout_2": 77.34,
            "NAWROCKI Karol Tadeusz_2": 263,
            "TRZASKOWSKI Rafał Kazimierz_2": 738
        },
        "calculations": {
            "issued_scale": 1.0555555555555556,
            "change_TRZASKOWSKI Rafał Kazimierz": 0.6584,
            "change_NAWROCKI Karol Tadeusz": 0.8014,
            "expected_nawrocki": 302.66,
            "expected_trzaskowski": 691.67,
            "delta_nawrocki": -39.664722222222224,
            "delta_trzaskowski": 46.331388888888796,
            "diff_pct_nawrocki": -0.1311,
            "delta_from_median_change": -0.0174,
            "delta_from_median_difference": -0.1353,
            "alert_index": 0.131,
            "change_TRZASKOWSKI Rafał Kazimierz_pct": 65.84,
            "change_NAWROCKI Karol Tadeusz_pct": 80.14,
            "diff_pct_nawrocki_pct": -13.11,
            "delta_from_median_change_pct": -1.74,
            "delta_from_median_difference_pct": -13.53,
            "alert_index_pct": 13.1
        },
        "alert_index_pct": 0.131,
        "alert_index": 0.131
    },
    {
        "commission": {
            "Nr komisji": "44",
            "Gmina": "m. Słupsk",
            "Teryt Gminy": "226301",
            "Powiat": "Słupsk",
            "Teryt Powiatu": "226300",
            "Województwo": "pomorskie",
            "Siedziba": "Wojewódzki Szpital Specjalistyczny im. Janusza Korczaka w Słupsku Sp. z o. o., ul. Hubalczyków 1, 76-200 Słupsk",
            "Typ obwodu": "zakład leczniczy",
            "Typ obszaru": "miasto",
            "id": "d8fe06f4cd5a313c6c485c1559693d95"
        },
        "turnout": {
            "first": "68.44% (154 z 225)",
            "second": "37.11% (180 z 485)",
            "scale": 0.5422267679719462
        },
        "first_round": {
            "eligible_voters_1": 225,
            "issued_1": 154,
            "turnout_1": 68.44,
            "BARTOSZEWICZ Artur_1": 2,
            "BIEJAT Magdalena Agnieszka_1": 5,
            "BRAUN Grzegorz Michał_1": 7,
            "HOŁOWNIA Szymon Franciszek_1": 9,
            "JAKUBIAK Marek_1": 1,
            "MACIAK Maciej_1": 0,
            "MENTZEN Sławomir Jerzy_1": 11,
            "NAWROCKI Karol Tadeusz_1": 47,
            "SENYSZYN Joanna_1": 0,
            "STANOWSKI Krzysztof Jakub_1": 5,
            "TRZASKOWSKI Rafał Kazimierz_1": 64,
            "WOCH Marek Marian_1": 0,
            "ZANDBERG Adrian Tadeusz_1": 1
        },
        "second_round": {
            "eligible_voters_2": 485,
            "issued_2": 180,
            "turnout_2": 37.11,
            "NAWROCKI Karol Tadeusz_2": 69,
            "TRZASKOWSKI Rafał Kazimierz_2": 107
        },
        "calculations": {
            "issued_scale": 1.1688311688311688,
            "change_TRZASKOWSKI Rafał Kazimierz": 0.6719,
            "change_NAWROCKI Karol Tadeusz": 0.4681,
            "expected_nawrocki": 79.4,
            "expected_trzaskowski": 94.76,
            "delta_nawrocki": -10.399870129870123,
            "delta_trzaskowski": 12.244025974025988,
            "diff_pct_nawrocki": -0.131,
            "delta_from_median_change": -0.3507,
            "delta_from_median_difference": -0.1352,
            "alert_index": 0.131,
            "change_TRZASKOWSKI Rafał Kazimierz_pct": 67.19,
            "change_NAWROCKI Karol Tadeusz_pct": 46.81,
            "diff_pct_nawrocki_pct": -13.1,
            "delta_from_median_change_pct": -35.07,
            "delta_from_median_difference_pct": -13.52,
            "alert_index_pct": 13.1
        },
        "alert_index_pct": 0.131,
        "alert_index": 0.131
    },
    {
        "commission": {
            "Nr komisji": "85",
            "Gmina": "m. Katowice",
            "Teryt Gminy": "246901",
            "Powiat": "Katowice",
            "Teryt Powiatu": "246900",
            "Województwo": "śląskie",
            "Siedziba": "Zespół Szkół i Placówek nr 1, ul. Ignacego Paderewskiego 46, 40-282 Katowice",
            "Typ obwodu": "stały",
            "Typ obszaru": "miasto",
            "id": "69634065a7595f3500529b07e3fc197f"
        },
        "turnout": {
            "first": "77.7% (1073 z 1381)",
            "second": "82.64% (1152 z 1394)",
            "scale": 1.0635778635778634
        },
        "first_round": {
            "eligible_voters_1": 1381,
            "issued_1": 1073,
            "turnout_1": 77.7,
            "BARTOSZEWICZ Artur_1": 1,
            "BIEJAT Magdalena Agnieszka_1": 48,
            "BRAUN Grzegorz Michał_1": 27,
            "HOŁOWNIA Szymon Franciszek_1": 62,
            "JAKUBIAK Marek_1": 4,
            "MACIAK Maciej_1": 0,
            "MENTZEN Sławomir Jerzy_1": 77,
            "NAWROCKI Karol Tadeusz_1": 225,
            "SENYSZYN Joanna_1": 15,
            "STANOWSKI Krzysztof Jakub_1": 8,
            "TRZASKOWSKI Rafał Kazimierz_1": 524,
            "WOCH Marek Marian_1": 0,
            "ZANDBERG Adrian Tadeusz_1": 81
        },
        "second_round": {
            "eligible_voters_2": 1394,
            "issued_2": 1152,
            "turnout_2": 82.64,
            "NAWROCKI Karol Tadeusz_2": 331,
            "TRZASKOWSKI Rafał Kazimierz_2": 814
        },
        "calculations": {
            "issued_scale": 1.0736253494874184,
            "change_TRZASKOWSKI Rafał Kazimierz": 0.5534,
            "change_NAWROCKI Karol Tadeusz": 0.4711,
            "expected_nawrocki": 380.91,
            "expected_trzaskowski": 764.65,
            "delta_nawrocki": -49.91153774464118,
            "delta_trzaskowski": 49.3532898415657,
            "diff_pct_nawrocki": -0.131,
            "delta_from_median_change": -0.3477,
            "delta_from_median_difference": -0.1352,
            "alert_index": 0.131,
            "change_TRZASKOWSKI Rafał Kazimierz_pct": 55.34,
            "change_NAWROCKI Karol Tadeusz_pct": 47.11,
            "diff_pct_nawrocki_pct": -13.1,
            "delta_from_median_change_pct": -34.77,
            "delta_from_median_difference_pct": -13.52,
            "alert_index_pct": 13.1
        },
        "alert_index_pct": 0.131,
        "alert_index": 0.131
    },
    {
        "commission": {
            "Nr komisji": "104",
            "Gmina": "m. Szczecin",
            "Teryt Gminy": "326201",
            "Powiat": "Szczecin",
            "Teryt Powiatu": "326200",
            "Województwo": "zachodniopomorskie",
            "Siedziba": "V Liceum Ogólnokształcące z Oddziałami Dwujęzycznymi, ul. Ofiar Oświęcimia 14, 71-537 Szczecin",
            "Typ obwodu": "stały",
            "Typ obszaru": "miasto",
            "id": "8f72bf4051e84bf8b20c3bfdfe1e29e7"
        },
        "turnout": {
            "first": "70.95% (1419 z 2000)",
            "second": "75.94% (1528 z 2012)",
            "scale": 1.0703312191684284
        },
        "first_round": {
            "eligible_voters_1": 2000,
            "issued_1": 1419,
            "turnout_1": 70.95,
            "BARTOSZEWICZ Artur_1": 2,
            "BIEJAT Magdalena Agnieszka_1": 86,
            "BRAUN Grzegorz Michał_1": 59,
            "HOŁOWNIA Szymon Franciszek_1": 70,
            "JAKUBIAK Marek_1": 7,
            "MACIAK Maciej_1": 1,
            "MENTZEN Sławomir Jerzy_1": 153,
            "NAWROCKI Karol Tadeusz_1": 276,
            "SENYSZYN Joanna_1": 11,
            "STANOWSKI Krzysztof Jakub_1": 18,
            "TRZASKOWSKI Rafał Kazimierz_1": 625,
            "WOCH Marek Marian_1": 1,
            "ZANDBERG Adrian Tadeusz_1": 99
        },
        "second_round": {
            "eligible_voters_2": 2012,
            "issued_2": 1528,
            "turnout_2": 75.94,
            "NAWROCKI Karol Tadeusz_2": 482,
            "TRZASKOWSKI Rafał Kazimierz_2": 1029
        },
        "calculations": {
            "issued_scale": 1.076814658210007,
            "change_TRZASKOWSKI Rafał Kazimierz": 0.6464,
            "change_NAWROCKI Karol Tadeusz": 0.7464,
            "expected_nawrocki": 554.67,
            "expected_trzaskowski": 949.64,
            "delta_nawrocki": -72.6747681465821,
            "delta_trzaskowski": 79.36469062720221,
            "diff_pct_nawrocki": -0.131,
            "delta_from_median_change": -0.0724,
            "delta_from_median_difference": -0.1352,
            "alert_index": 0.131,
            "change_TRZASKOWSKI Rafał Kazimierz_pct": 64.64,
            "change_NAWROCKI Karol Tadeusz_pct": 74.64,
            "diff_pct_nawrocki_pct": -13.1,
            "delta_from_median_change_pct": -7.24,
            "delta_from_median_difference_pct": -13.52,
            "alert_index_pct": 13.1
        },
        "alert_index_pct": 0.131,
        "alert_index": 0.131
    },
    {
        "commission": {
            "Nr komisji": "57",
            "Gmina": "m. Wrocław",
            "Teryt Gminy": "26401",
            "Powiat": "Wrocław",
            "Teryt Powiatu": "26400",
            "Województwo": "dolnośląskie",
            "Siedziba": "Centrum Kreatywności TALENT (Poradnia Psychologiczno-Pedagogiczna nr 2), ul. Jedności Narodowej 117, 50-301 Wrocław",
            "Typ obwodu": "stały",
            "Typ obszaru": "miasto",
            "id": "998f65b673af2e27752e6c4c51e8fad0"
        },
        "turnout": {
            "first": "66.43% (1116 z 1680)",
            "second": "71.79% (1224 z 1705)",
            "scale": 1.0806864368508204
        },
        "first_round": {
            "eligible_voters_1": 1680,
            "issued_1": 1116,
            "turnout_1": 66.43,
            "BARTOSZEWICZ Artur_1": 6,
            "BIEJAT Magdalena Agnieszka_1": 88,
            "BRAUN Grzegorz Michał_1": 33,
            "HOŁOWNIA Szymon Franciszek_1": 46,
            "JAKUBIAK Marek_1": 9,
            "MACIAK Maciej_1": 3,
            "MENTZEN Sławomir Jerzy_1": 120,
            "NAWROCKI Karol Tadeusz_1": 196,
            "SENYSZYN Joanna_1": 22,
            "STANOWSKI Krzysztof Jakub_1": 11,
            "TRZASKOWSKI Rafał Kazimierz_1": 404,
            "WOCH Marek Marian_1": 2,
            "ZANDBERG Adrian Tadeusz_1": 176
        },
        "second_round": {
            "eligible_voters_2": 1705,
            "issued_2": 1224,
            "turnout_2": 71.79,
            "NAWROCKI Karol Tadeusz_2": 370,
            "TRZASKOWSKI Rafał Kazimierz_2": 836
        },
        "calculations": {
            "issued_scale": 1.096774193548387,
            "change_TRZASKOWSKI Rafał Kazimierz": 1.0693,
            "change_NAWROCKI Karol Tadeusz": 0.8878,
            "expected_nawrocki": 425.75,
            "expected_trzaskowski": 776.31,
            "delta_nawrocki": -55.75348387096773,
            "delta_trzaskowski": 59.6889677419357,
            "diff_pct_nawrocki": -0.131,
            "delta_from_median_change": 0.069,
            "delta_from_median_difference": -0.1352,
            "alert_index": 0.1309,
            "change_TRZASKOWSKI Rafał Kazimierz_pct": 106.93,
            "change_NAWROCKI Karol Tadeusz_pct": 88.78,
            "diff_pct_nawrocki_pct": -13.1,
            "delta_from_median_change_pct": 6.9,
            "delta_from_median_difference_pct": -13.52,
            "alert_index_pct": 13.09
        },
        "alert_index_pct": 0.1309,
        "alert_index": 0.1309
    },
    {
        "commission": {
            "Nr komisji": "26",
            "Gmina": "gm. Zielonki",
            "Teryt Gminy": "120617",
            "Powiat": "krakowski",
            "Teryt Powiatu": "120600",
            "Województwo": "małopolskie",
            "Siedziba": "Dom Pomocy Społecznej w Owczarach, ul. Kasztanowa 20, 32-088 Owczary",
            "Typ obwodu": "dom pomocy społecznej",
            "Typ obszaru": "wieś",
            "id": "b40bf6895f9bb80c12b973774512f0fc"
        },
        "turnout": {
            "first": "40.63% (26 z 64)",
            "second": "39.68% (25 z 63)",
            "scale": 0.9766182623677085
        },
        "first_round": {
            "eligible_voters_1": 64,
            "issued_1": 26,
            "turnout_1": 40.63,
            "BARTOSZEWICZ Artur_1": 1,
            "BIEJAT Magdalena Agnieszka_1": 1,
            "BRAUN Grzegorz Michał_1": 1,
            "HOŁOWNIA Szymon Franciszek_1": 2,
            "JAKUBIAK Marek_1": 0,
            "MACIAK Maciej_1": 0,
            "MENTZEN Sławomir Jerzy_1": 1,
            "NAWROCKI Karol Tadeusz_1": 4,
            "SENYSZYN Joanna_1": 0,
            "STANOWSKI Krzysztof Jakub_1": 0,
            "TRZASKOWSKI Rafał Kazimierz_1": 12,
            "WOCH Marek Marian_1": 1,
            "ZANDBERG Adrian Tadeusz_1": 1
        },
        "second_round": {
            "eligible_voters_2": 63,
            "issued_2": 25,
            "turnout_2": 39.68,
            "NAWROCKI Karol Tadeusz_2": 7,
            "TRZASKOWSKI Rafał Kazimierz_2": 16
        },
        "calculations": {
            "issued_scale": 0.9615384615384616,
            "change_TRZASKOWSKI Rafał Kazimierz": 0.3333,
            "change_NAWROCKI Karol Tadeusz": 0.75,
            "expected_nawrocki": 6.19,
            "expected_trzaskowski": 14.97,
            "delta_nawrocki": 0.8134615384615387,
            "delta_trzaskowski": 1.032692307692308,
            "diff_pct_nawrocki": 0.1315,
            "delta_from_median_change": -0.0688,
            "delta_from_median_difference": 0.1273,
            "alert_index": 0.1309,
            "change_TRZASKOWSKI Rafał Kazimierz_pct": 33.33,
            "change_NAWROCKI Karol Tadeusz_pct": 75,
            "diff_pct_nawrocki_pct": 13.15,
            "delta_from_median_change_pct": -6.88,
            "delta_from_median_difference_pct": 12.73,
            "alert_index_pct": 13.09
        },
        "alert_index_pct": 0.1309,
        "alert_index": 0.1309
    },
    {
        "commission": {
            "Nr komisji": "3",
            "Gmina": "gm. Wysoka",
            "Teryt Gminy": "301909",
            "Powiat": "pilski",
            "Teryt Powiatu": "301900",
            "Województwo": "wielkopolskie",
            "Siedziba": "Świetlica Wiejska, Rudna 1a, 89-320 Wysoka",
            "Typ obwodu": "stały",
            "Typ obszaru": "wieś",
            "id": "5a77adf5563894420ec0529eba826d4c"
        },
        "turnout": {
            "first": "51.41% (91 z 177)",
            "second": "50% (87 z 174)",
            "scale": 0.9725734292939118
        },
        "first_round": {
            "eligible_voters_1": 177,
            "issued_1": 91,
            "turnout_1": 51.41,
            "BARTOSZEWICZ Artur_1": 1,
            "BIEJAT Magdalena Agnieszka_1": 8,
            "BRAUN Grzegorz Michał_1": 6,
            "HOŁOWNIA Szymon Franciszek_1": 5,
            "JAKUBIAK Marek_1": 0,
            "MACIAK Maciej_1": 0,
            "MENTZEN Sławomir Jerzy_1": 22,
            "NAWROCKI Karol Tadeusz_1": 25,
            "SENYSZYN Joanna_1": 1,
            "STANOWSKI Krzysztof Jakub_1": 0,
            "TRZASKOWSKI Rafał Kazimierz_1": 22,
            "WOCH Marek Marian_1": 0,
            "ZANDBERG Adrian Tadeusz_1": 1
        },
        "second_round": {
            "eligible_voters_2": 174,
            "issued_2": 87,
            "turnout_2": 50,
            "NAWROCKI Karol Tadeusz_2": 56,
            "TRZASKOWSKI Rafał Kazimierz_2": 31
        },
        "calculations": {
            "issued_scale": 0.9560439560439561,
            "change_TRZASKOWSKI Rafał Kazimierz": 0.4091,
            "change_NAWROCKI Karol Tadeusz": 1.24,
            "expected_nawrocki": 49.52,
            "expected_trzaskowski": 36.52,
            "delta_nawrocki": 6.47501098901099,
            "delta_trzaskowski": -5.518967032967026,
            "diff_pct_nawrocki": 0.1307,
            "delta_from_median_change": 0.4212,
            "delta_from_median_difference": 0.1265,
            "alert_index": 0.1309,
            "change_TRZASKOWSKI Rafał Kazimierz_pct": 40.91,
            "change_NAWROCKI Karol Tadeusz_pct": 124,
            "diff_pct_nawrocki_pct": 13.07,
            "delta_from_median_change_pct": 42.12,
            "delta_from_median_difference_pct": 12.65,
            "alert_index_pct": 13.09
        },
        "alert_index_pct": 0.1309,
        "alert_index": 0.1309
    }
]