[
    {
        "commission": {
            "Nr komisji": "5",
            "Gmina": "gm. Mircze",
            "Teryt Gminy": "60405",
            "Powiat": "hrubieszowski",
            "Teryt Powiatu": "60400",
            "Województwo": "lubelskie",
            "Siedziba": "Świetlica Wiejska, Górka-Zabłocie ul. Kościelna 1, 22-530 Mircze",
            "Typ obwodu": "stały",
            "Typ obszaru": "wieś",
            "id": "7171f06866853cc4736f79bee6a152ca"
        },
        "turnout": {
            "first": "55.26% (210 z 380)",
            "second": "58.49% (224 z 383)",
            "scale": 1.058450959102425
        },
        "first_round": {
            "eligible_voters_1": 380,
            "issued_1": 210,
            "turnout_1": 55.26,
            "BARTOSZEWICZ Artur_1": 0,
            "BIEJAT Magdalena Agnieszka_1": 6,
            "BRAUN Grzegorz Michał_1": 19,
            "HOŁOWNIA Szymon Franciszek_1": 4,
            "JAKUBIAK Marek_1": 0,
            "MACIAK Maciej_1": 0,
            "MENTZEN Sławomir Jerzy_1": 27,
            "NAWROCKI Karol Tadeusz_1": 122,
            "SENYSZYN Joanna_1": 1,
            "STANOWSKI Krzysztof Jakub_1": 3,
            "TRZASKOWSKI Rafał Kazimierz_1": 19,
            "WOCH Marek Marian_1": 0,
            "ZANDBERG Adrian Tadeusz_1": 6
        },
        "second_round": {
            "eligible_voters_2": 383,
            "issued_2": 224,
            "turnout_2": 58.49,
            "NAWROCKI Karol Tadeusz_2": 192,
            "TRZASKOWSKI Rafał Kazimierz_2": 32
        },
        "calculations": {
            "issued_scale": 1.0666666666666667,
            "change_TRZASKOWSKI Rafał Kazimierz": 0.6842,
            "change_NAWROCKI Karol Tadeusz": 0.5738,
            "expected_nawrocki": 177.64,
            "expected_trzaskowski": 43.16,
            "delta_nawrocki": 14.362666666666684,
            "delta_trzaskowski": -11.162666666666652,
            "diff_pct_nawrocki": 0.0809,
            "delta_from_median_change": -0.245,
            "delta_from_median_difference": 0.0767,
            "alert_index": 0.0808,
            "change_TRZASKOWSKI Rafał Kazimierz_pct": 68.42,
            "change_NAWROCKI Karol Tadeusz_pct": 57.38,
            "diff_pct_nawrocki_pct": 8.09,
            "delta_from_median_change_pct": -24.5,
            "delta_from_median_difference_pct": 7.67,
            "alert_index_pct": 8.08
        },
        "alert_index_pct": 0.0808,
        "alert_index": 0.0808
    },
    {
        "commission": {
            "Nr komisji": "4",
            "Gmina": "gm. Łęczyca",
            "Teryt Gminy": "100405",
            "Powiat": "łęczycki",
            "Teryt Powiatu": "100400",
            "Województwo": "łódzkie",
            "Siedziba": "Szkoła Podstawowa, Leźnica Mała 36, 99-100 Łęczyca",
            "Typ obwodu": "stały",
            "Typ obszaru": "wieś",
            "id": "ccdf16178e0423e95b794bcf0d07e31e"
        },
        "turnout": {
            "first": "62.92% (560 z 890)",
            "second": "67.61% (599 z 886)",
            "scale": 1.07453909726637
        },
        "first_round": {
            "eligible_voters_1": 890,
            "issued_1": 560,
            "turnout_1": 62.92,
            "BARTOSZEWICZ Artur_1": 3,
            "BIEJAT Magdalena Agnieszka_1": 19,
            "BRAUN Grzegorz Michał_1": 38,
            "HOŁOWNIA Szymon Franciszek_1": 20,
            "JAKUBIAK Marek_1": 7,
            "MACIAK Maciej_1": 5,
            "MENTZEN Sławomir Jerzy_1": 112,
            "NAWROCKI Karol Tadeusz_1": 234,
            "SENYSZYN Joanna_1": 4,
            "STANOWSKI Krzysztof Jakub_1": 3,
            "TRZASKOWSKI Rafał Kazimierz_1": 95,
            "WOCH Marek Marian_1": 0,
            "ZANDBERG Adrian Tadeusz_1": 19
        },
        "second_round": {
            "eligible_voters_2": 886,
            "issued_2": 599,
            "turnout_2": 67.61,
            "NAWROCKI Karol Tadeusz_2": 436,
            "TRZASKOWSKI Rafał Kazimierz_2": 160
        },
        "calculations": {
            "issued_scale": 1.0696428571428571,
            "change_TRZASKOWSKI Rafał Kazimierz": 0.6842,
            "change_NAWROCKI Karol Tadeusz": 0.8632,
            "expected_nawrocki": 403.39,
            "expected_trzaskowski": 178.5,
            "delta_nawrocki": 32.60986785714289,
            "delta_trzaskowski": -18.49558214285713,
            "diff_pct_nawrocki": 0.0808,
            "delta_from_median_change": 0.0444,
            "delta_from_median_difference": 0.0766,
            "alert_index": 0.0808,
            "change_TRZASKOWSKI Rafał Kazimierz_pct": 68.42,
            "change_NAWROCKI Karol Tadeusz_pct": 86.32,
            "diff_pct_nawrocki_pct": 8.08,
            "delta_from_median_change_pct": 4.44,
            "delta_from_median_difference_pct": 7.66,
            "alert_index_pct": 8.08
        },
        "alert_index_pct": 0.0808,
        "alert_index": 0.0808
    },
    {
        "commission": {
            "Nr komisji": "4",
            "Gmina": "gm. Nadarzyn",
            "Teryt Gminy": "142105",
            "Powiat": "pruszkowski",
            "Teryt Powiatu": "142100",
            "Województwo": "mazowieckie",
            "Siedziba": "Szkoła Podstawowa, Rusiec ul. Osiedlowa 72, 05-830 Nadarzyn",
            "Typ obwodu": "stały",
            "Typ obszaru": "wieś",
            "id": "2ec88761b1166698c9e2478ac7d0c602"
        },
        "turnout": {
            "first": "77.61% (1116 z 1438)",
            "second": "81.66% (1220 z 1494)",
            "scale": 1.052183996907615
        },
        "first_round": {
            "eligible_voters_1": 1438,
            "issued_1": 1116,
            "turnout_1": 77.61,
            "BARTOSZEWICZ Artur_1": 2,
            "BIEJAT Magdalena Agnieszka_1": 55,
            "BRAUN Grzegorz Michał_1": 72,
            "HOŁOWNIA Szymon Franciszek_1": 59,
            "JAKUBIAK Marek_1": 16,
            "MACIAK Maciej_1": 2,
            "MENTZEN Sławomir Jerzy_1": 162,
            "NAWROCKI Karol Tadeusz_1": 228,
            "SENYSZYN Joanna_1": 25,
            "STANOWSKI Krzysztof Jakub_1": 25,
            "TRZASKOWSKI Rafał Kazimierz_1": 424,
            "WOCH Marek Marian_1": 1,
            "ZANDBERG Adrian Tadeusz_1": 41
        },
        "second_round": {
            "eligible_voters_2": 1494,
            "issued_2": 1220,
            "turnout_2": 81.66,
            "NAWROCKI Karol Tadeusz_2": 480,
            "TRZASKOWSKI Rafał Kazimierz_2": 727
        },
        "calculations": {
            "issued_scale": 1.093189964157706,
            "change_TRZASKOWSKI Rafał Kazimierz": 0.7146,
            "change_NAWROCKI Karol Tadeusz": 1.1053,
            "expected_nawrocki": 522.18,
            "expected_trzaskowski": 670.49,
            "delta_nawrocki": -42.178584229390594,
            "delta_trzaskowski": 56.508333333333326,
            "diff_pct_nawrocki": -0.0808,
            "delta_from_median_change": 0.2865,
            "delta_from_median_difference": -0.085,
            "alert_index": 0.0808,
            "change_TRZASKOWSKI Rafał Kazimierz_pct": 71.46,
            "change_NAWROCKI Karol Tadeusz_pct": 110.53,
            "diff_pct_nawrocki_pct": -8.08,
            "delta_from_median_change_pct": 28.65,
            "delta_from_median_difference_pct": -8.5,
            "alert_index_pct": 8.08
        },
        "alert_index_pct": 0.0808,
        "alert_index": 0.0808
    },
    {
        "commission": {
            "Nr komisji": "977",
            "Gmina": "Rembertów",
            "Teryt Gminy": "146509",
            "Powiat": "Warszawa",
            "Teryt Powiatu": "146501",
            "Województwo": "mazowieckie",
            "Siedziba": "Przedszkole Nr 376 z Oddziałami Integracyjnymi w Warszawie, ul. Admiralska 17, 00-910 Warszawa",
            "Typ obwodu": "stały",
            "Typ obszaru": "dzielnica w m.st. Warszawa",
            "id": "9175629c468ec2a1b34a7e8809227b99"
        },
        "turnout": {
            "first": "82.96% (1110 z 1338)",
            "second": "86.5% (1128 z 1304)",
            "scale": 1.0426711668273867
        },
        "first_round": {
            "eligible_voters_1": 1338,
            "issued_1": 1110,
            "turnout_1": 82.96,
            "BARTOSZEWICZ Artur_1": 7,
            "BIEJAT Magdalena Agnieszka_1": 75,
            "BRAUN Grzegorz Michał_1": 38,
            "HOŁOWNIA Szymon Franciszek_1": 56,
            "JAKUBIAK Marek_1": 9,
            "MACIAK Maciej_1": 0,
            "MENTZEN Sławomir Jerzy_1": 112,
            "NAWROCKI Karol Tadeusz_1": 152,
            "SENYSZYN Joanna_1": 20,
            "STANOWSKI Krzysztof Jakub_1": 26,
            "TRZASKOWSKI Rafał Kazimierz_1": 561,
            "WOCH Marek Marian_1": 0,
            "ZANDBERG Adrian Tadeusz_1": 51
        },
        "second_round": {
            "eligible_voters_2": 1304,
            "issued_2": 1128,
            "turnout_2": 86.5,
            "NAWROCKI Karol Tadeusz_2": 309,
            "TRZASKOWSKI Rafał Kazimierz_2": 811
        },
        "calculations": {
            "issued_scale": 1.0162162162162163,
            "change_TRZASKOWSKI Rafał Kazimierz": 0.4456,
            "change_NAWROCKI Karol Tadeusz": 1.0329,
            "expected_nawrocki": 336.16,
            "expected_trzaskowski": 772.53,
            "delta_nawrocki": -27.16432432432441,
            "delta_trzaskowski": 38.47243243243247,
            "diff_pct_nawrocki": -0.0808,
            "delta_from_median_change": 0.2141,
            "delta_from_median_difference": -0.085,
            "alert_index": 0.0808,
            "change_TRZASKOWSKI Rafał Kazimierz_pct": 44.56,
            "change_NAWROCKI Karol Tadeusz_pct": 103.29,
            "diff_pct_nawrocki_pct": -8.08,
            "delta_from_median_change_pct": 21.41,
            "delta_from_median_difference_pct": -8.5,
            "alert_index_pct": 8.08
        },
        "alert_index_pct": 0.0808,
        "alert_index": 0.0808
    },
    {
        "commission": {
            "Nr komisji": "928",
            "Gmina": "Targówek",
            "Teryt Gminy": "146511",
            "Powiat": "Warszawa",
            "Teryt Powiatu": "146501",
            "Województwo": "mazowieckie",
            "Siedziba": "Szkoła Podstawowa z Oddziałami Integracyjnymi Nr 42 im. K. I. Gałczyńskiego, ul. Balkonowa 4, 03-329 Warszawa",
            "Typ obwodu": "stały",
            "Typ obszaru": "dzielnica w m.st. Warszawa",
            "id": "a59905d01ac6c8792035c399e22762de"
        },
        "turnout": {
            "first": "75.3% (1143 z 1518)",
            "second": "77.88% (1190 z 1528)",
            "scale": 1.0342629482071712
        },
        "first_round": {
            "eligible_voters_1": 1518,
            "issued_1": 1143,
            "turnout_1": 75.3,
            "BARTOSZEWICZ Artur_1": 10,
            "BIEJAT Magdalena Agnieszka_1": 63,
            "BRAUN Grzegorz Michał_1": 48,
            "HOŁOWNIA Szymon Franciszek_1": 59,
            "JAKUBIAK Marek_1": 11,
            "MACIAK Maciej_1": 1,
            "MENTZEN Sławomir Jerzy_1": 108,
            "NAWROCKI Karol Tadeusz_1": 302,
            "SENYSZYN Joanna_1": 20,
            "STANOWSKI Krzysztof Jakub_1": 28,
            "TRZASKOWSKI Rafał Kazimierz_1": 415,
            "WOCH Marek Marian_1": 0,
            "ZANDBERG Adrian Tadeusz_1": 74
        },
        "second_round": {
            "eligible_voters_2": 1528,
            "issued_2": 1190,
            "turnout_2": 77.88,
            "NAWROCKI Karol Tadeusz_2": 467,
            "TRZASKOWSKI Rafał Kazimierz_2": 711
        },
        "calculations": {
            "issued_scale": 1.0411198600174978,
            "change_TRZASKOWSKI Rafał Kazimierz": 0.7133,
            "change_NAWROCKI Karol Tadeusz": 0.5464,
            "expected_nawrocki": 508.07,
            "expected_trzaskowski": 654.86,
            "delta_nawrocki": -41.070656167978996,
            "delta_trzaskowski": 56.13977252843381,
            "diff_pct_nawrocki": -0.0808,
            "delta_from_median_change": -0.2724,
            "delta_from_median_difference": -0.085,
            "alert_index": 0.0808,
            "change_TRZASKOWSKI Rafał Kazimierz_pct": 71.33,
            "change_NAWROCKI Karol Tadeusz_pct": 54.64,
            "diff_pct_nawrocki_pct": -8.08,
            "delta_from_median_change_pct": -27.24,
            "delta_from_median_difference_pct": -8.5,
            "alert_index_pct": 8.08
        },
        "alert_index_pct": 0.0808,
        "alert_index": 0.0808
    },
    {
        "commission": {
            "Nr komisji": "529",
            "Gmina": "Wawer",
            "Teryt Gminy": "146514",
            "Powiat": "Warszawa",
            "Teryt Powiatu": "146501",
            "Województwo": "mazowieckie",
            "Siedziba": "Hala Sportowa, ul. Poezji 5, 04-984 Warszawa",
            "Typ obwodu": "stały",
            "Typ obszaru": "dzielnica w m.st. Warszawa",
            "id": "344745ab356d66801a90707f307c176b"
        },
        "turnout": {
            "first": "81.7% (1277 z 1563)",
            "second": "84.84% (1371 z 1616)",
            "scale": 1.0384332925336597
        },
        "first_round": {
            "eligible_voters_1": 1563,
            "issued_1": 1277,
            "turnout_1": 81.7,
            "BARTOSZEWICZ Artur_1": 4,
            "BIEJAT Magdalena Agnieszka_1": 75,
            "BRAUN Grzegorz Michał_1": 63,
            "HOŁOWNIA Szymon Franciszek_1": 79,
            "JAKUBIAK Marek_1": 10,
            "MACIAK Maciej_1": 2,
            "MENTZEN Sławomir Jerzy_1": 173,
            "NAWROCKI Karol Tadeusz_1": 257,
            "SENYSZYN Joanna_1": 17,
            "STANOWSKI Krzysztof Jakub_1": 19,
            "TRZASKOWSKI Rafał Kazimierz_1": 481,
            "WOCH Marek Marian_1": 1,
            "ZANDBERG Adrian Tadeusz_1": 92
        },
        "second_round": {
            "eligible_voters_2": 1616,
            "issued_2": 1371,
            "turnout_2": 84.84,
            "NAWROCKI Karol Tadeusz_2": 510,
            "TRZASKOWSKI Rafał Kazimierz_2": 850
        },
        "calculations": {
            "issued_scale": 1.0736100234925607,
            "change_TRZASKOWSKI Rafał Kazimierz": 0.7672,
            "change_NAWROCKI Karol Tadeusz": 0.9844,
            "expected_nawrocki": 554.84,
            "expected_trzaskowski": 793.62,
            "delta_nawrocki": -44.83736570086148,
            "delta_trzaskowski": 56.383176194205134,
            "diff_pct_nawrocki": -0.0808,
            "delta_from_median_change": 0.1656,
            "delta_from_median_difference": -0.085,
            "alert_index": 0.0808,
            "change_TRZASKOWSKI Rafał Kazimierz_pct": 76.72,
            "change_NAWROCKI Karol Tadeusz_pct": 98.44,
            "diff_pct_nawrocki_pct": -8.08,
            "delta_from_median_change_pct": 16.56,
            "delta_from_median_difference_pct": -8.5,
            "alert_index_pct": 8.08
        },
        "alert_index_pct": 0.0808,
        "alert_index": 0.0808
    },
    {
        "commission": {
            "Nr komisji": "11",
            "Gmina": "gm. Jeżowe",
            "Teryt Gminy": "181203",
            "Powiat": "niżański",
            "Teryt Powiatu": "181200",
            "Województwo": "podkarpackie",
            "Siedziba": "Świetlica OSP w Nowym Narcie, Nowy Nart 41, 37-430 Jeżowe",
            "Typ obwodu": "stały",
            "Typ obszaru": "wieś",
            "id": "ef8442b664d0965b94ff0e0861e084fd"
        },
        "turnout": {
            "first": "57.68% (214 z 371)",
            "second": "61.33% (222 z 362)",
            "scale": 1.0632801664355063
        },
        "first_round": {
            "eligible_voters_1": 371,
            "issued_1": 214,
            "turnout_1": 57.68,
            "BARTOSZEWICZ Artur_1": 0,
            "BIEJAT Magdalena Agnieszka_1": 2,
            "BRAUN Grzegorz Michał_1": 11,
            "HOŁOWNIA Szymon Franciszek_1": 3,
            "JAKUBIAK Marek_1": 1,
            "MACIAK Maciej_1": 0,
            "MENTZEN Sławomir Jerzy_1": 44,
            "NAWROCKI Karol Tadeusz_1": 134,
            "SENYSZYN Joanna_1": 3,
            "STANOWSKI Krzysztof Jakub_1": 2,
            "TRZASKOWSKI Rafał Kazimierz_1": 10,
            "WOCH Marek Marian_1": 0,
            "ZANDBERG Adrian Tadeusz_1": 2
        },
        "second_round": {
            "eligible_voters_2": 362,
            "issued_2": 222,
            "turnout_2": 61.33,
            "NAWROCKI Karol Tadeusz_2": 207,
            "TRZASKOWSKI Rafał Kazimierz_2": 14
        },
        "calculations": {
            "issued_scale": 1.0373831775700935,
            "change_TRZASKOWSKI Rafał Kazimierz": 0.4,
            "change_NAWROCKI Karol Tadeusz": 0.5448,
            "expected_nawrocki": 191.53,
            "expected_trzaskowski": 27.36,
            "delta_nawrocki": 15.472093457943885,
            "delta_trzaskowski": -13.359943925233647,
            "diff_pct_nawrocki": 0.0808,
            "delta_from_median_change": -0.274,
            "delta_from_median_difference": 0.0766,
            "alert_index": 0.0808,
            "change_TRZASKOWSKI Rafał Kazimierz_pct": 40,
            "change_NAWROCKI Karol Tadeusz_pct": 54.48,
            "diff_pct_nawrocki_pct": 8.08,
            "delta_from_median_change_pct": -27.4,
            "delta_from_median_difference_pct": 7.66,
            "alert_index_pct": 8.08
        },
        "alert_index_pct": 0.0808,
        "alert_index": 0.0808
    },
    {
        "commission": {
            "Nr komisji": "1",
            "Gmina": "gm. Grajewo",
            "Teryt Gminy": "200402",
            "Powiat": "grajewski",
            "Teryt Powiatu": "200400",
            "Województwo": "podlaskie",
            "Siedziba": "Urząd Gminy Grajewo, ul. Komunalna 6, 19-200 Grajewo",
            "Typ obwodu": "stały",
            "Typ obszaru": "wieś",
            "id": "aeb552588d7c8bb39d1f07bf30c59a3c"
        },
        "turnout": {
            "first": "54.69% (437 z 799)",
            "second": "54.77% (436 z 796)",
            "scale": 1.001462790272445
        },
        "first_round": {
            "eligible_voters_1": 799,
            "issued_1": 437,
            "turnout_1": 54.69,
            "BARTOSZEWICZ Artur_1": 5,
            "BIEJAT Magdalena Agnieszka_1": 8,
            "BRAUN Grzegorz Michał_1": 70,
            "HOŁOWNIA Szymon Franciszek_1": 15,
            "JAKUBIAK Marek_1": 4,
            "MACIAK Maciej_1": 3,
            "MENTZEN Sławomir Jerzy_1": 92,
            "NAWROCKI Karol Tadeusz_1": 171,
            "SENYSZYN Joanna_1": 10,
            "STANOWSKI Krzysztof Jakub_1": 4,
            "TRZASKOWSKI Rafał Kazimierz_1": 40,
            "WOCH Marek Marian_1": 0,
            "ZANDBERG Adrian Tadeusz_1": 11
        },
        "second_round": {
            "eligible_voters_2": 796,
            "issued_2": 436,
            "turnout_2": 54.77,
            "NAWROCKI Karol Tadeusz_2": 350,
            "TRZASKOWSKI Rafał Kazimierz_2": 83
        },
        "calculations": {
            "issued_scale": 0.9977116704805492,
            "change_TRZASKOWSKI Rafał Kazimierz": 1.075,
            "change_NAWROCKI Karol Tadeusz": 1.0468,
            "expected_nawrocki": 323.84,
            "expected_trzaskowski": 96.2,
            "delta_nawrocki": 26.16374370709383,
            "delta_trzaskowski": -13.20035697940503,
            "diff_pct_nawrocki": 0.0808,
            "delta_from_median_change": 0.228,
            "delta_from_median_difference": 0.0766,
            "alert_index": 0.0808,
            "change_TRZASKOWSKI Rafał Kazimierz_pct": 107.5,
            "change_NAWROCKI Karol Tadeusz_pct": 104.68,
            "diff_pct_nawrocki_pct": 8.08,
            "delta_from_median_change_pct": 22.8,
            "delta_from_median_difference_pct": 7.66,
            "alert_index_pct": 8.08
        },
        "alert_index_pct": 0.0808,
        "alert_index": 0.0808
    },
    {
        "commission": {
            "Nr komisji": "14",
            "Gmina": "gm. Wejherowo",
            "Teryt Gminy": "221510",
            "Powiat": "wejherowski",
            "Teryt Powiatu": "221500",
            "Województwo": "pomorskie",
            "Siedziba": "Świetlica wiejska, ul. Królowej Jadwigi 1, 84-200 Kąpino",
            "Typ obwodu": "stały",
            "Typ obszaru": "wieś",
            "id": "c0865b15f4533aca97f3a300d1c3cb49"
        },
        "turnout": {
            "first": "80.25% (821 z 1023)",
            "second": "83.65% (875 z 1046)",
            "scale": 1.042367601246106
        },
        "first_round": {
            "eligible_voters_1": 1023,
            "issued_1": 821,
            "turnout_1": 80.25,
            "BARTOSZEWICZ Artur_1": 3,
            "BIEJAT Magdalena Agnieszka_1": 39,
            "BRAUN Grzegorz Michał_1": 35,
            "HOŁOWNIA Szymon Franciszek_1": 63,
            "JAKUBIAK Marek_1": 4,
            "MACIAK Maciej_1": 0,
            "MENTZEN Sławomir Jerzy_1": 105,
            "NAWROCKI Karol Tadeusz_1": 111,
            "SENYSZYN Joanna_1": 6,
            "STANOWSKI Krzysztof Jakub_1": 7,
            "TRZASKOWSKI Rafał Kazimierz_1": 395,
            "WOCH Marek Marian_1": 1,
            "ZANDBERG Adrian Tadeusz_1": 50
        },
        "second_round": {
            "eligible_voters_2": 1046,
            "issued_2": 875,
            "turnout_2": 83.65,
            "NAWROCKI Karol Tadeusz_2": 259,
            "TRZASKOWSKI Rafał Kazimierz_2": 609
        },
        "calculations": {
            "issued_scale": 1.0657734470158344,
            "change_TRZASKOWSKI Rafał Kazimierz": 0.5418,
            "change_NAWROCKI Karol Tadeusz": 1.3333,
            "expected_nawrocki": 281.78,
            "expected_trzaskowski": 582.57,
            "delta_nawrocki": -22.776644336175366,
            "delta_trzaskowski": 26.434378806333598,
            "diff_pct_nawrocki": -0.0808,
            "delta_from_median_change": 0.5145,
            "delta_from_median_difference": -0.085,
            "alert_index": 0.0808,
            "change_TRZASKOWSKI Rafał Kazimierz_pct": 54.18,
            "change_NAWROCKI Karol Tadeusz_pct": 133.33,
            "diff_pct_nawrocki_pct": -8.08,
            "delta_from_median_change_pct": 51.45,
            "delta_from_median_difference_pct": -8.5,
            "alert_index_pct": 8.08
        },
        "alert_index_pct": 0.0808,
        "alert_index": 0.0808
    },
    {
        "commission": {
            "Nr komisji": "4",
            "Gmina": "gm. Opatowiec",
            "Teryt Gminy": "260304",
            "Powiat": "kazimierski",
            "Teryt Powiatu": "260300",
            "Województwo": "świętokrzyskie",
            "Siedziba": "Klub Seniora w Kocinie, Kocina 131, 28-520 Opatowiec",
            "Typ obwodu": "stały",
            "Typ obszaru": "wieś",
            "id": "61d99f83058c64e1cac8ebe791060849"
        },
        "turnout": {
            "first": "59.74% (184 z 308)",
            "second": "64.09% (191 z 298)",
            "scale": 1.0728155339805825
        },
        "first_round": {
            "eligible_voters_1": 308,
            "issued_1": 184,
            "turnout_1": 59.74,
            "BARTOSZEWICZ Artur_1": 1,
            "BIEJAT Magdalena Agnieszka_1": 7,
            "BRAUN Grzegorz Michał_1": 21,
            "HOŁOWNIA Szymon Franciszek_1": 11,
            "JAKUBIAK Marek_1": 0,
            "MACIAK Maciej_1": 0,
            "MENTZEN Sławomir Jerzy_1": 34,
            "NAWROCKI Karol Tadeusz_1": 64,
            "SENYSZYN Joanna_1": 4,
            "STANOWSKI Krzysztof Jakub_1": 0,
            "TRZASKOWSKI Rafał Kazimierz_1": 39,
            "WOCH Marek Marian_1": 0,
            "ZANDBERG Adrian Tadeusz_1": 3
        },
        "second_round": {
            "eligible_voters_2": 298,
            "issued_2": 191,
            "turnout_2": 64.09,
            "NAWROCKI Karol Tadeusz_2": 131,
            "TRZASKOWSKI Rafał Kazimierz_2": 60
        },
        "calculations": {
            "issued_scale": 1.0380434782608696,
            "change_TRZASKOWSKI Rafał Kazimierz": 0.5385,
            "change_NAWROCKI Karol Tadeusz": 1.0469,
            "expected_nawrocki": 121.21,
            "expected_trzaskowski": 68.75,
            "delta_nawrocki": 9.790777173913042,
            "delta_trzaskowski": -8.752733695652182,
            "diff_pct_nawrocki": 0.0808,
            "delta_from_median_change": 0.2281,
            "delta_from_median_difference": 0.0766,
            "alert_index": 0.0808,
            "change_TRZASKOWSKI Rafał Kazimierz_pct": 53.85,
            "change_NAWROCKI Karol Tadeusz_pct": 104.69,
            "diff_pct_nawrocki_pct": 8.08,
            "delta_from_median_change_pct": 22.81,
            "delta_from_median_difference_pct": 7.66,
            "alert_index_pct": 8.08
        },
        "alert_index_pct": 0.0808,
        "alert_index": 0.0808
    },
    {
        "commission": {
            "Nr komisji": "3",
            "Gmina": "gm. Chodów",
            "Teryt Gminy": "300903",
            "Powiat": "kolski",
            "Teryt Powiatu": "300900",
            "Województwo": "wielkopolskie",
            "Siedziba": "Świetlica wiejska w Czerwonce, Czerwonka 2a, 62-652 Chodów",
            "Typ obwodu": "stały",
            "Typ obszaru": "wieś",
            "id": "375b5c2b88e9210ab7a0d42d21624540"
        },
        "turnout": {
            "first": "55.27% (341 z 617)",
            "second": "61.74% (376 z 609)",
            "scale": 1.1170616971232132
        },
        "first_round": {
            "eligible_voters_1": 617,
            "issued_1": 341,
            "turnout_1": 55.27,
            "BARTOSZEWICZ Artur_1": 4,
            "BIEJAT Magdalena Agnieszka_1": 11,
            "BRAUN Grzegorz Michał_1": 25,
            "HOŁOWNIA Szymon Franciszek_1": 6,
            "JAKUBIAK Marek_1": 1,
            "MACIAK Maciej_1": 4,
            "MENTZEN Sławomir Jerzy_1": 80,
            "NAWROCKI Karol Tadeusz_1": 169,
            "SENYSZYN Joanna_1": 4,
            "STANOWSKI Krzysztof Jakub_1": 1,
            "TRZASKOWSKI Rafał Kazimierz_1": 26,
            "WOCH Marek Marian_1": 0,
            "ZANDBERG Adrian Tadeusz_1": 7
        },
        "second_round": {
            "eligible_voters_2": 609,
            "issued_2": 376,
            "turnout_2": 61.74,
            "NAWROCKI Karol Tadeusz_2": 317,
            "TRZASKOWSKI Rafał Kazimierz_2": 57
        },
        "calculations": {
            "issued_scale": 1.1026392961876832,
            "change_TRZASKOWSKI Rafał Kazimierz": 1.1923,
            "change_NAWROCKI Karol Tadeusz": 0.8757,
            "expected_nawrocki": 293.29,
            "expected_trzaskowski": 69.48,
            "delta_nawrocki": 23.70897360703816,
            "delta_trzaskowski": -12.477302052785916,
            "diff_pct_nawrocki": 0.0808,
            "delta_from_median_change": 0.0569,
            "delta_from_median_difference": 0.0766,
            "alert_index": 0.0808,
            "change_TRZASKOWSKI Rafał Kazimierz_pct": 119.23,
            "change_NAWROCKI Karol Tadeusz_pct": 87.57,
            "diff_pct_nawrocki_pct": 8.08,
            "delta_from_median_change_pct": 5.69,
            "delta_from_median_difference_pct": 7.66,
            "alert_index_pct": 8.08
        },
        "alert_index_pct": 0.0808,
        "alert_index": 0.0808
    },
    {
        "commission": {
            "Nr komisji": "12",
            "Gmina": "m. Piła",
            "Teryt Gminy": "301901",
            "Powiat": "pilski",
            "Teryt Powiatu": "301900",
            "Województwo": "wielkopolskie",
            "Siedziba": "Liceum Ogólnokształcące Towarzystwa Salezjańskiego im. Św. Jana Bosko, ul. Edwarda Dembowskiego 4, 64-920 Piła",
            "Typ obwodu": "stały",
            "Typ obszaru": "miasto",
            "id": "db3b53d742ac20e3bfe114cfe4c1368b"
        },
        "turnout": {
            "first": "74.27% (1250 z 1683)",
            "second": "77.84% (1275 z 1638)",
            "scale": 1.048067860508954
        },
        "first_round": {
            "eligible_voters_1": 1683,
            "issued_1": 1250,
            "turnout_1": 74.27,
            "BARTOSZEWICZ Artur_1": 7,
            "BIEJAT Magdalena Agnieszka_1": 35,
            "BRAUN Grzegorz Michał_1": 35,
            "HOŁOWNIA Szymon Franciszek_1": 72,
            "JAKUBIAK Marek_1": 6,
            "MACIAK Maciej_1": 1,
            "MENTZEN Sławomir Jerzy_1": 151,
            "NAWROCKI Karol Tadeusz_1": 293,
            "SENYSZYN Joanna_1": 11,
            "STANOWSKI Krzysztof Jakub_1": 17,
            "TRZASKOWSKI Rafał Kazimierz_1": 565,
            "WOCH Marek Marian_1": 1,
            "ZANDBERG Adrian Tadeusz_1": 54
        },
        "second_round": {
            "eligible_voters_2": 1638,
            "issued_2": 1275,
            "turnout_2": 77.84,
            "NAWROCKI Karol Tadeusz_2": 464,
            "TRZASKOWSKI Rafał Kazimierz_2": 801
        },
        "calculations": {
            "issued_scale": 1.02,
            "change_TRZASKOWSKI Rafał Kazimierz": 0.4177,
            "change_NAWROCKI Karol Tadeusz": 0.5836,
            "expected_nawrocki": 504.8,
            "expected_trzaskowski": 752.86,
            "delta_nawrocki": -40.80004000000008,
            "delta_trzaskowski": 48.140039999999885,
            "diff_pct_nawrocki": -0.0808,
            "delta_from_median_change": -0.2352,
            "delta_from_median_difference": -0.085,
            "alert_index": 0.0808,
            "change_TRZASKOWSKI Rafał Kazimierz_pct": 41.77,
            "change_NAWROCKI Karol Tadeusz_pct": 58.36,
            "diff_pct_nawrocki_pct": -8.08,
            "delta_from_median_change_pct": -23.52,
            "delta_from_median_difference_pct": -8.5,
            "alert_index_pct": 8.08
        },
        "alert_index_pct": 0.0808,
        "alert_index": 0.0808
    },
    {
        "commission": {
            "Nr komisji": "13",
            "Gmina": "gm. Rudna",
            "Teryt Gminy": "21103",
            "Powiat": "lubiński",
            "Teryt Powiatu": "21100",
            "Województwo": "dolnośląskie",
            "Siedziba": "Świetlica Wiejska, Naroczyce 48\/1, 59-305 Rudna",
            "Typ obwodu": "stały",
            "Typ obszaru": "wieś",
            "id": "f95e9fa407bd5ac293685264daedc55d"
        },
        "turnout": {
            "first": "61.04% (188 z 308)",
            "second": "69.06% (212 z 307)",
            "scale": 1.131389252948886
        },
        "first_round": {
            "eligible_voters_1": 308,
            "issued_1": 188,
            "turnout_1": 61.04,
            "BARTOSZEWICZ Artur_1": 2,
            "BIEJAT Magdalena Agnieszka_1": 7,
            "BRAUN Grzegorz Michał_1": 19,
            "HOŁOWNIA Szymon Franciszek_1": 1,
            "JAKUBIAK Marek_1": 2,
            "MACIAK Maciej_1": 0,
            "MENTZEN Sławomir Jerzy_1": 46,
            "NAWROCKI Karol Tadeusz_1": 64,
            "SENYSZYN Joanna_1": 5,
            "STANOWSKI Krzysztof Jakub_1": 1,
            "TRZASKOWSKI Rafał Kazimierz_1": 31,
            "WOCH Marek Marian_1": 0,
            "ZANDBERG Adrian Tadeusz_1": 8
        },
        "second_round": {
            "eligible_voters_2": 307,
            "issued_2": 212,
            "turnout_2": 69.06,
            "NAWROCKI Karol Tadeusz_2": 153,
            "TRZASKOWSKI Rafał Kazimierz_2": 57
        },
        "calculations": {
            "issued_scale": 1.127659574468085,
            "change_TRZASKOWSKI Rafał Kazimierz": 0.8387,
            "change_NAWROCKI Karol Tadeusz": 1.3906,
            "expected_nawrocki": 141.57,
            "expected_trzaskowski": 63.67,
            "delta_nawrocki": 11.433617021276604,
            "delta_trzaskowski": -6.667659574468082,
            "diff_pct_nawrocki": 0.0808,
            "delta_from_median_change": 0.5718,
            "delta_from_median_difference": 0.0766,
            "alert_index": 0.0807,
            "change_TRZASKOWSKI Rafał Kazimierz_pct": 83.87,
            "change_NAWROCKI Karol Tadeusz_pct": 139.06,
            "diff_pct_nawrocki_pct": 8.08,
            "delta_from_median_change_pct": 57.18,
            "delta_from_median_difference_pct": 7.66,
            "alert_index_pct": 8.07
        },
        "alert_index_pct": 0.0807,
        "alert_index": 0.0807
    },
    {
        "commission": {
            "Nr komisji": "11",
            "Gmina": "gm. Oborniki Śląskie",
            "Teryt Gminy": "22001",
            "Powiat": "trzebnicki",
            "Teryt Powiatu": "22000",
            "Województwo": "dolnośląskie",
            "Siedziba": "Szkoła Podstawowa, Osolin ul. marsz. Józefa Piłsudskiego 5, 55-120 Oborniki Śląskie",
            "Typ obwodu": "stały",
            "Typ obszaru": "wieś",
            "id": "445c5d6cd759ed9c541f35011df45347"
        },
        "turnout": {
            "first": "66.71% (499 z 748)",
            "second": "73.53% (564 z 767)",
            "scale": 1.1022335481936743
        },
        "first_round": {
            "eligible_voters_1": 748,
            "issued_1": 499,
            "turnout_1": 66.71,
            "BARTOSZEWICZ Artur_1": 1,
            "BIEJAT Magdalena Agnieszka_1": 27,
            "BRAUN Grzegorz Michał_1": 35,
            "HOŁOWNIA Szymon Franciszek_1": 26,
            "JAKUBIAK Marek_1": 4,
            "MACIAK Maciej_1": 1,
            "MENTZEN Sławomir Jerzy_1": 54,
            "NAWROCKI Karol Tadeusz_1": 151,
            "SENYSZYN Joanna_1": 1,
            "STANOWSKI Krzysztof Jakub_1": 6,
            "TRZASKOWSKI Rafał Kazimierz_1": 166,
            "WOCH Marek Marian_1": 1,
            "ZANDBERG Adrian Tadeusz_1": 21
        },
        "second_round": {
            "eligible_voters_2": 767,
            "issued_2": 564,
            "turnout_2": 73.53,
            "NAWROCKI Karol Tadeusz_2": 254,
            "TRZASKOWSKI Rafał Kazimierz_2": 303
        },
        "calculations": {
            "issued_scale": 1.1302605210420842,
            "change_TRZASKOWSKI Rafał Kazimierz": 0.8253,
            "change_NAWROCKI Karol Tadeusz": 0.6821,
            "expected_nawrocki": 276.29,
            "expected_trzaskowski": 274.15,
            "delta_nawrocki": -22.29105410821643,
            "delta_trzaskowski": 28.854180360721443,
            "diff_pct_nawrocki": -0.0807,
            "delta_from_median_change": -0.1367,
            "delta_from_median_difference": -0.0849,
            "alert_index": 0.0807,
            "change_TRZASKOWSKI Rafał Kazimierz_pct": 82.53,
            "change_NAWROCKI Karol Tadeusz_pct": 68.21,
            "diff_pct_nawrocki_pct": -8.07,
            "delta_from_median_change_pct": -13.67,
            "delta_from_median_difference_pct": -8.49,
            "alert_index_pct": 8.07
        },
        "alert_index_pct": 0.0807,
        "alert_index": 0.0807
    },
    {
        "commission": {
            "Nr komisji": "7",
            "Gmina": "gm. Jeżewo",
            "Teryt Gminy": "41404",
            "Powiat": "świecki",
            "Teryt Powiatu": "41400",
            "Województwo": "kujawsko-pomorskie",
            "Siedziba": "Świetlica wiejska Taszewskie Pole, Taszewskie Pole 30, 86-131 Jeżewo",
            "Typ obwodu": "stały",
            "Typ obszaru": "wieś",
            "id": "6f5f328025944357f1bede006b0d3165"
        },
        "turnout": {
            "first": "56.15% (210 z 374)",
            "second": "60.16% (225 z 374)",
            "scale": 1.0714158504007123
        },
        "first_round": {
            "eligible_voters_1": 374,
            "issued_1": 210,
            "turnout_1": 56.15,
            "BARTOSZEWICZ Artur_1": 0,
            "BIEJAT Magdalena Agnieszka_1": 11,
            "BRAUN Grzegorz Michał_1": 24,
            "HOŁOWNIA Szymon Franciszek_1": 17,
            "JAKUBIAK Marek_1": 0,
            "MACIAK Maciej_1": 0,
            "MENTZEN Sławomir Jerzy_1": 39,
            "NAWROCKI Karol Tadeusz_1": 72,
            "SENYSZYN Joanna_1": 0,
            "STANOWSKI Krzysztof Jakub_1": 2,
            "TRZASKOWSKI Rafał Kazimierz_1": 38,
            "WOCH Marek Marian_1": 0,
            "ZANDBERG Adrian Tadeusz_1": 6
        },
        "second_round": {
            "eligible_voters_2": 374,
            "issued_2": 225,
            "turnout_2": 60.16,
            "NAWROCKI Karol Tadeusz_2": 155,
            "TRZASKOWSKI Rafał Kazimierz_2": 67
        },
        "calculations": {
            "issued_scale": 1.0714285714285714,
            "change_TRZASKOWSKI Rafał Kazimierz": 0.7632,
            "change_NAWROCKI Karol Tadeusz": 1.1528,
            "expected_nawrocki": 143.42,
            "expected_trzaskowski": 80.51,
            "delta_nawrocki": 11.583928571428544,
            "delta_trzaskowski": -13.512499999999989,
            "diff_pct_nawrocki": 0.0808,
            "delta_from_median_change": 0.334,
            "delta_from_median_difference": 0.0766,
            "alert_index": 0.0807,
            "change_TRZASKOWSKI Rafał Kazimierz_pct": 76.32,
            "change_NAWROCKI Karol Tadeusz_pct": 115.28,
            "diff_pct_nawrocki_pct": 8.08,
            "delta_from_median_change_pct": 33.4,
            "delta_from_median_difference_pct": 7.66,
            "alert_index_pct": 8.07
        },
        "alert_index_pct": 0.0807,
        "alert_index": 0.0807
    },
    {
        "commission": {
            "Nr komisji": "9",
            "Gmina": "gm. Ryńsk",
            "Teryt Gminy": "41705",
            "Powiat": "wąbrzeski",
            "Teryt Powiatu": "41700",
            "Województwo": "kujawsko-pomorskie",
            "Siedziba": "Świetlica, Wronie 24B, 87-200 Wąbrzeźno",
            "Typ obwodu": "stały",
            "Typ obszaru": "wieś",
            "id": "857c9a804d4c28631af69531d9143474"
        },
        "turnout": {
            "first": "57.69% (225 z 390)",
            "second": "60.93% (237 z 389)",
            "scale": 1.0561622464898597
        },
        "first_round": {
            "eligible_voters_1": 390,
            "issued_1": 225,
            "turnout_1": 57.69,
            "BARTOSZEWICZ Artur_1": 0,
            "BIEJAT Magdalena Agnieszka_1": 13,
            "BRAUN Grzegorz Michał_1": 16,
            "HOŁOWNIA Szymon Franciszek_1": 19,
            "JAKUBIAK Marek_1": 3,
            "MACIAK Maciej_1": 0,
            "MENTZEN Sławomir Jerzy_1": 38,
            "NAWROCKI Karol Tadeusz_1": 57,
            "SENYSZYN Joanna_1": 2,
            "STANOWSKI Krzysztof Jakub_1": 2,
            "TRZASKOWSKI Rafał Kazimierz_1": 71,
            "WOCH Marek Marian_1": 0,
            "ZANDBERG Adrian Tadeusz_1": 4
        },
        "second_round": {
            "eligible_voters_2": 389,
            "issued_2": 237,
            "turnout_2": 60.93,
            "NAWROCKI Karol Tadeusz_2": 108,
            "TRZASKOWSKI Rafał Kazimierz_2": 128
        },
        "calculations": {
            "issued_scale": 1.0533333333333332,
            "change_TRZASKOWSKI Rafał Kazimierz": 0.8028,
            "change_NAWROCKI Karol Tadeusz": 0.8947,
            "expected_nawrocki": 117.48,
            "expected_trzaskowski": 116.36,
            "delta_nawrocki": -9.483533333333327,
            "delta_trzaskowski": 11.643533333333338,
            "diff_pct_nawrocki": -0.0807,
            "delta_from_median_change": 0.0759,
            "delta_from_median_difference": -0.0849,
            "alert_index": 0.0807,
            "change_TRZASKOWSKI Rafał Kazimierz_pct": 80.28,
            "change_NAWROCKI Karol Tadeusz_pct": 89.47,
            "diff_pct_nawrocki_pct": -8.07,
            "delta_from_median_change_pct": 7.59,
            "delta_from_median_difference_pct": -8.49,
            "alert_index_pct": 8.07
        },
        "alert_index_pct": 0.0807,
        "alert_index": 0.0807
    },
    {
        "commission": {
            "Nr komisji": "7",
            "Gmina": "gm. Żółkiewka",
            "Teryt Gminy": "60611",
            "Powiat": "krasnostawski",
            "Teryt Powiatu": "60600",
            "Województwo": "lubelskie",
            "Siedziba": "Remiza OSP, Wierzchowina 165, 22-335 Żółkiewka",
            "Typ obwodu": "stały",
            "Typ obszaru": "wieś",
            "id": "10288f61a69612f3814b42e08e4ec4f9"
        },
        "turnout": {
            "first": "56.89% (194 z 341)",
            "second": "57.43% (197 z 343)",
            "scale": 1.0094920021093339
        },
        "first_round": {
            "eligible_voters_1": 341,
            "issued_1": 194,
            "turnout_1": 56.89,
            "BARTOSZEWICZ Artur_1": 1,
            "BIEJAT Magdalena Agnieszka_1": 2,
            "BRAUN Grzegorz Michał_1": 18,
            "HOŁOWNIA Szymon Franciszek_1": 3,
            "JAKUBIAK Marek_1": 4,
            "MACIAK Maciej_1": 0,
            "MENTZEN Sławomir Jerzy_1": 40,
            "NAWROCKI Karol Tadeusz_1": 107,
            "SENYSZYN Joanna_1": 2,
            "STANOWSKI Krzysztof Jakub_1": 1,
            "TRZASKOWSKI Rafał Kazimierz_1": 9,
            "WOCH Marek Marian_1": 1,
            "ZANDBERG Adrian Tadeusz_1": 4
        },
        "second_round": {
            "eligible_voters_2": 343,
            "issued_2": 197,
            "turnout_2": 57.43,
            "NAWROCKI Karol Tadeusz_2": 176,
            "TRZASKOWSKI Rafał Kazimierz_2": 18
        },
        "calculations": {
            "issued_scale": 1.0154639175257731,
            "change_TRZASKOWSKI Rafał Kazimierz": 1,
            "change_NAWROCKI Karol Tadeusz": 0.6449,
            "expected_nawrocki": 162.86,
            "expected_trzaskowski": 26.02,
            "delta_nawrocki": 13.140912371134021,
            "delta_trzaskowski": -8.017201030927836,
            "diff_pct_nawrocki": 0.0807,
            "delta_from_median_change": -0.1739,
            "delta_from_median_difference": 0.0765,
            "alert_index": 0.0807,
            "change_TRZASKOWSKI Rafał Kazimierz_pct": 100,
            "change_NAWROCKI Karol Tadeusz_pct": 64.49,
            "diff_pct_nawrocki_pct": 8.07,
            "delta_from_median_change_pct": -17.39,
            "delta_from_median_difference_pct": 7.65,
            "alert_index_pct": 8.07
        },
        "alert_index_pct": 0.0807,
        "alert_index": 0.0807
    },
    {
        "commission": {
            "Nr komisji": "5",
            "Gmina": "gm. Lipnica Murowana",
            "Teryt Gminy": "120104",
            "Powiat": "bocheński",
            "Teryt Powiatu": "120100",
            "Województwo": "małopolskie",
            "Siedziba": "Publiczna Szkoła Podstawowa im. św. Jana Pawła II w Rajbrocie, Rajbrot 362, 32-725 Rajbrot",
            "Typ obwodu": "stały",
            "Typ obszaru": "wieś",
            "id": "1d4af78d68f8f128c8e293815ecda4df"
        },
        "turnout": {
            "first": "68.49% (1165 z 1701)",
            "second": "71.89% (1220 z 1697)",
            "scale": 1.0496422835450432
        },
        "first_round": {
            "eligible_voters_1": 1701,
            "issued_1": 1165,
            "turnout_1": 68.49,
            "BARTOSZEWICZ Artur_1": 3,
            "BIEJAT Magdalena Agnieszka_1": 11,
            "BRAUN Grzegorz Michał_1": 97,
            "HOŁOWNIA Szymon Franciszek_1": 32,
            "JAKUBIAK Marek_1": 4,
            "MACIAK Maciej_1": 2,
            "MENTZEN Sławomir Jerzy_1": 240,
            "NAWROCKI Karol Tadeusz_1": 658,
            "SENYSZYN Joanna_1": 9,
            "STANOWSKI Krzysztof Jakub_1": 11,
            "TRZASKOWSKI Rafał Kazimierz_1": 69,
            "WOCH Marek Marian_1": 1,
            "ZANDBERG Adrian Tadeusz_1": 24
        },
        "second_round": {
            "eligible_voters_2": 1697,
            "issued_2": 1220,
            "turnout_2": 71.89,
            "NAWROCKI Karol Tadeusz_2": 1100,
            "TRZASKOWSKI Rafał Kazimierz_2": 116
        },
        "calculations": {
            "issued_scale": 1.0472103004291846,
            "change_TRZASKOWSKI Rafał Kazimierz": 0.6812,
            "change_NAWROCKI Karol Tadeusz": 0.6717,
            "expected_nawrocki": 1017.85,
            "expected_trzaskowski": 187.49,
            "delta_nawrocki": 82.14928755364804,
            "delta_trzaskowski": -71.48834334763947,
            "diff_pct_nawrocki": 0.0807,
            "delta_from_median_change": -0.1471,
            "delta_from_median_difference": 0.0765,
            "alert_index": 0.0807,
            "change_TRZASKOWSKI Rafał Kazimierz_pct": 68.12,
            "change_NAWROCKI Karol Tadeusz_pct": 67.17,
            "diff_pct_nawrocki_pct": 8.07,
            "delta_from_median_change_pct": -14.71,
            "delta_from_median_difference_pct": 7.65,
            "alert_index_pct": 8.07
        },
        "alert_index_pct": 0.0807,
        "alert_index": 0.0807
    },
    {
        "commission": {
            "Nr komisji": "163",
            "Gmina": "m. Kraków",
            "Teryt Gminy": "126101",
            "Powiat": "Kraków",
            "Teryt Powiatu": "126100",
            "Województwo": "małopolskie",
            "Siedziba": "Zespół Szkolno-Przedszkolny Nr 8, ul. Mieczysława Wrony 115, 30-399 Kraków",
            "Typ obwodu": "stały",
            "Typ obszaru": "miasto",
            "id": "65649c9087a84578047f93742faf4a46"
        },
        "turnout": {
            "first": "79.36% (1219 z 1536)",
            "second": "82.45% (1273 z 1544)",
            "scale": 1.038936491935484
        },
        "first_round": {
            "eligible_voters_1": 1536,
            "issued_1": 1219,
            "turnout_1": 79.36,
            "BARTOSZEWICZ Artur_1": 8,
            "BIEJAT Magdalena Agnieszka_1": 56,
            "BRAUN Grzegorz Michał_1": 65,
            "HOŁOWNIA Szymon Franciszek_1": 105,
            "JAKUBIAK Marek_1": 16,
            "MACIAK Maciej_1": 2,
            "MENTZEN Sławomir Jerzy_1": 189,
            "NAWROCKI Karol Tadeusz_1": 237,
            "SENYSZYN Joanna_1": 18,
            "STANOWSKI Krzysztof Jakub_1": 24,
            "TRZASKOWSKI Rafał Kazimierz_1": 420,
            "WOCH Marek Marian_1": 1,
            "ZANDBERG Adrian Tadeusz_1": 72
        },
        "second_round": {
            "eligible_voters_2": 1544,
            "issued_2": 1273,
            "turnout_2": 82.45,
            "NAWROCKI Karol Tadeusz_2": 493,
            "TRZASKOWSKI Rafał Kazimierz_2": 764
        },
        "calculations": {
            "issued_scale": 1.044298605414274,
            "change_TRZASKOWSKI Rafał Kazimierz": 0.819,
            "change_NAWROCKI Karol Tadeusz": 1.0802,
            "expected_nawrocki": 536.25,
            "expected_trzaskowski": 702.28,
            "delta_nawrocki": -43.25464397046767,
            "delta_trzaskowski": 61.71649794913856,
            "diff_pct_nawrocki": -0.0807,
            "delta_from_median_change": 0.2614,
            "delta_from_median_difference": -0.0849,
            "alert_index": 0.0807,
            "change_TRZASKOWSKI Rafał Kazimierz_pct": 81.9,
            "change_NAWROCKI Karol Tadeusz_pct": 108.02,
            "diff_pct_nawrocki_pct": -8.07,
            "delta_from_median_change_pct": 26.14,
            "delta_from_median_difference_pct": -8.49,
            "alert_index_pct": 8.07
        },
        "alert_index_pct": 0.0807,
        "alert_index": 0.0807
    },
    {
        "commission": {
            "Nr komisji": "19",
            "Gmina": "m. Lębork",
            "Teryt Gminy": "220801",
            "Powiat": "lęborski",
            "Teryt Powiatu": "220800",
            "Województwo": "pomorskie",
            "Siedziba": "Szkoła Podstawowa Nr 5, Sala Gimnastyczna, Wejście B, ul. Kościuszki 14, 84-300 Lębork",
            "Typ obwodu": "stały",
            "Typ obszaru": "miasto",
            "id": "6244ffda64e49fad685836e6774001b0"
        },
        "turnout": {
            "first": "61.25% (743 z 1213)",
            "second": "63.97% (776 z 1213)",
            "scale": 1.0444081632653062
        },
        "first_round": {
            "eligible_voters_1": 1213,
            "issued_1": 743,
            "turnout_1": 61.25,
            "BARTOSZEWICZ Artur_1": 3,
            "BIEJAT Magdalena Agnieszka_1": 41,
            "BRAUN Grzegorz Michał_1": 40,
            "HOŁOWNIA Szymon Franciszek_1": 46,
            "JAKUBIAK Marek_1": 2,
            "MACIAK Maciej_1": 0,
            "MENTZEN Sławomir Jerzy_1": 134,
            "NAWROCKI Karol Tadeusz_1": 145,
            "SENYSZYN Joanna_1": 5,
            "STANOWSKI Krzysztof Jakub_1": 5,
            "TRZASKOWSKI Rafał Kazimierz_1": 285,
            "WOCH Marek Marian_1": 0,
            "ZANDBERG Adrian Tadeusz_1": 31
        },
        "second_round": {
            "eligible_voters_2": 1213,
            "issued_2": 776,
            "turnout_2": 63.97,
            "NAWROCKI Karol Tadeusz_2": 308,
            "TRZASKOWSKI Rafał Kazimierz_2": 463
        },
        "calculations": {
            "issued_scale": 1.044414535666218,
            "change_TRZASKOWSKI Rafał Kazimierz": 0.6246,
            "change_NAWROCKI Karol Tadeusz": 1.1241,
            "expected_nawrocki": 335.03,
            "expected_trzaskowski": 429.48,
            "delta_nawrocki": -27.02938358008072,
            "delta_trzaskowski": 33.51794347240923,
            "diff_pct_nawrocki": -0.0807,
            "delta_from_median_change": 0.3053,
            "delta_from_median_difference": -0.0849,
            "alert_index": 0.0807,
            "change_TRZASKOWSKI Rafał Kazimierz_pct": 62.46,
            "change_NAWROCKI Karol Tadeusz_pct": 112.41,
            "diff_pct_nawrocki_pct": -8.07,
            "delta_from_median_change_pct": 30.53,
            "delta_from_median_difference_pct": -8.49,
            "alert_index_pct": 8.07
        },
        "alert_index_pct": 0.0807,
        "alert_index": 0.0807
    },
    {
        "commission": {
            "Nr komisji": "2",
            "Gmina": "gm. Opalenica",
            "Teryt Gminy": "301505",
            "Powiat": "nowotomyski",
            "Teryt Powiatu": "301500",
            "Województwo": "wielkopolskie",
            "Siedziba": "Opalenicka Aula Kulturalno-Rozrywkowa, ul. Zamkowa 3A, 64-330 Opalenica",
            "Typ obwodu": "stały",
            "Typ obszaru": "miasto",
            "id": "e94611a543e650b00db7eae24a4d4ea0"
        },
        "turnout": {
            "first": "70.82% (1039 z 1467)",
            "second": "72.33% (1043 z 1442)",
            "scale": 1.0213216605478679
        },
        "first_round": {
            "eligible_voters_1": 1467,
            "issued_1": 1039,
            "turnout_1": 70.82,
            "BARTOSZEWICZ Artur_1": 2,
            "BIEJAT Magdalena Agnieszka_1": 59,
            "BRAUN Grzegorz Michał_1": 53,
            "HOŁOWNIA Szymon Franciszek_1": 58,
            "JAKUBIAK Marek_1": 9,
            "MACIAK Maciej_1": 2,
            "MENTZEN Sławomir Jerzy_1": 144,
            "NAWROCKI Karol Tadeusz_1": 242,
            "SENYSZYN Joanna_1": 13,
            "STANOWSKI Krzysztof Jakub_1": 13,
            "TRZASKOWSKI Rafał Kazimierz_1": 392,
            "WOCH Marek Marian_1": 1,
            "ZANDBERG Adrian Tadeusz_1": 48
        },
        "second_round": {
            "eligible_voters_2": 1442,
            "issued_2": 1043,
            "turnout_2": 72.33,
            "NAWROCKI Karol Tadeusz_2": 416,
            "TRZASKOWSKI Rafał Kazimierz_2": 614
        },
        "calculations": {
            "issued_scale": 1.0038498556304138,
            "change_TRZASKOWSKI Rafał Kazimierz": 0.5663,
            "change_NAWROCKI Karol Tadeusz": 0.719,
            "expected_nawrocki": 452.53,
            "expected_trzaskowski": 573.41,
            "delta_nawrocki": -36.52547641963429,
            "delta_trzaskowski": 40.59092396535141,
            "diff_pct_nawrocki": -0.0807,
            "delta_from_median_change": -0.0998,
            "delta_from_median_difference": -0.0849,
            "alert_index": 0.0807,
            "change_TRZASKOWSKI Rafał Kazimierz_pct": 56.63,
            "change_NAWROCKI Karol Tadeusz_pct": 71.9,
            "diff_pct_nawrocki_pct": -8.07,
            "delta_from_median_change_pct": -9.98,
            "delta_from_median_difference_pct": -8.49,
            "alert_index_pct": 8.07
        },
        "alert_index_pct": 0.0807,
        "alert_index": 0.0807
    },
    {
        "commission": {
            "Nr komisji": "158",
            "Gmina": "m. Łódź",
            "Teryt Gminy": "106101",
            "Powiat": "Łódź",
            "Teryt Powiatu": "106100",
            "Województwo": "łódzkie",
            "Siedziba": "Szkoła Podstawowa nr 160 im. Powstańców Śląskich, ul. Andrzeja Struga 24A, 90-513 Łódź",
            "Typ obwodu": "stały",
            "Typ obszaru": "miasto",
            "id": "d2086ea7314203d981b00d456a039523"
        },
        "turnout": {
            "first": "58.13% (633 z 1089)",
            "second": "61.9% (666 z 1076)",
            "scale": 1.0648546361603302
        },
        "first_round": {
            "eligible_voters_1": 1089,
            "issued_1": 633,
            "turnout_1": 58.13,
            "BARTOSZEWICZ Artur_1": 4,
            "BIEJAT Magdalena Agnieszka_1": 29,
            "BRAUN Grzegorz Michał_1": 48,
            "HOŁOWNIA Szymon Franciszek_1": 36,
            "JAKUBIAK Marek_1": 1,
            "MACIAK Maciej_1": 2,
            "MENTZEN Sławomir Jerzy_1": 72,
            "NAWROCKI Karol Tadeusz_1": 145,
            "SENYSZYN Joanna_1": 7,
            "STANOWSKI Krzysztof Jakub_1": 9,
            "TRZASKOWSKI Rafał Kazimierz_1": 216,
            "WOCH Marek Marian_1": 0,
            "ZANDBERG Adrian Tadeusz_1": 64
        },
        "second_round": {
            "eligible_voters_2": 1076,
            "issued_2": 666,
            "turnout_2": 61.9,
            "NAWROCKI Karol Tadeusz_2": 269,
            "TRZASKOWSKI Rafał Kazimierz_2": 392
        },
        "calculations": {
            "issued_scale": 1.052132701421801,
            "change_TRZASKOWSKI Rafał Kazimierz": 0.8148,
            "change_NAWROCKI Karol Tadeusz": 0.8552,
            "expected_nawrocki": 292.58,
            "expected_trzaskowski": 366.05,
            "delta_nawrocki": -23.583374407582937,
            "delta_trzaskowski": 25.94830331753559,
            "diff_pct_nawrocki": -0.0806,
            "delta_from_median_change": 0.0364,
            "delta_from_median_difference": -0.0848,
            "alert_index": 0.0806,
            "change_TRZASKOWSKI Rafał Kazimierz_pct": 81.48,
            "change_NAWROCKI Karol Tadeusz_pct": 85.52,
            "diff_pct_nawrocki_pct": -8.06,
            "delta_from_median_change_pct": 3.64,
            "delta_from_median_difference_pct": -8.48,
            "alert_index_pct": 8.06
        },
        "alert_index_pct": 0.0806,
        "alert_index": 0.0806
    },
    {
        "commission": {
            "Nr komisji": "133",
            "Gmina": "Mokotów",
            "Teryt Gminy": "146505",
            "Powiat": "Warszawa",
            "Teryt Powiatu": "146501",
            "Województwo": "mazowieckie",
            "Siedziba": "Przedszkole z oddziałami integracyjnymi Nr 326 \"Chatka Skrzatka\", ul. Bernardyńska 14, 02-904 Warszawa",
            "Typ obwodu": "stały",
            "Typ obszaru": "dzielnica w m.st. Warszawa",
            "id": "0d1c6193ad78786013c8618363da5471"
        },
        "turnout": {
            "first": "82.16% (1755 z 2136)",
            "second": "87.04% (1854 z 2130)",
            "scale": 1.0593962999026292
        },
        "first_round": {
            "eligible_voters_1": 2136,
            "issued_1": 1755,
            "turnout_1": 82.16,
            "BARTOSZEWICZ Artur_1": 5,
            "BIEJAT Magdalena Agnieszka_1": 126,
            "BRAUN Grzegorz Michał_1": 45,
            "HOŁOWNIA Szymon Franciszek_1": 103,
            "JAKUBIAK Marek_1": 11,
            "MACIAK Maciej_1": 2,
            "MENTZEN Sławomir Jerzy_1": 115,
            "NAWROCKI Karol Tadeusz_1": 230,
            "SENYSZYN Joanna_1": 42,
            "STANOWSKI Krzysztof Jakub_1": 23,
            "TRZASKOWSKI Rafał Kazimierz_1": 931,
            "WOCH Marek Marian_1": 2,
            "ZANDBERG Adrian Tadeusz_1": 104
        },
        "second_round": {
            "eligible_voters_2": 2130,
            "issued_2": 1854,
            "turnout_2": 87.04,
            "NAWROCKI Karol Tadeusz_2": 431,
            "TRZASKOWSKI Rafał Kazimierz_2": 1405
        },
        "calculations": {
            "issued_scale": 1.0564102564102564,
            "change_TRZASKOWSKI Rafał Kazimierz": 0.5091,
            "change_NAWROCKI Karol Tadeusz": 0.8739,
            "expected_nawrocki": 468.8,
            "expected_trzaskowski": 1347.17,
            "delta_nawrocki": -37.79684102564107,
            "delta_trzaskowski": 57.82761025641025,
            "diff_pct_nawrocki": -0.0806,
            "delta_from_median_change": 0.0551,
            "delta_from_median_difference": -0.0848,
            "alert_index": 0.0806,
            "change_TRZASKOWSKI Rafał Kazimierz_pct": 50.91,
            "change_NAWROCKI Karol Tadeusz_pct": 87.39,
            "diff_pct_nawrocki_pct": -8.06,
            "delta_from_median_change_pct": 5.51,
            "delta_from_median_difference_pct": -8.48,
            "alert_index_pct": 8.06
        },
        "alert_index_pct": 0.0806,
        "alert_index": 0.0806
    },
    {
        "commission": {
            "Nr komisji": "472",
            "Gmina": "Praga-Południe",
            "Teryt Gminy": "146507",
            "Powiat": "Warszawa",
            "Teryt Powiatu": "146501",
            "Województwo": "mazowieckie",
            "Siedziba": "Szkoła Podstawowa nr 312, ul. Władysława Umińskiego 12, 03-984 Warszawa",
            "Typ obwodu": "stały",
            "Typ obszaru": "dzielnica w m.st. Warszawa",
            "id": "74d0dacacd00068d747e260f36368398"
        },
        "turnout": {
            "first": "80.34% (1418 z 1765)",
            "second": "85.1% (1473 z 1731)",
            "scale": 1.059248195170525
        },
        "first_round": {
            "eligible_voters_1": 1765,
            "issued_1": 1418,
            "turnout_1": 80.34,
            "BARTOSZEWICZ Artur_1": 7,
            "BIEJAT Magdalena Agnieszka_1": 86,
            "BRAUN Grzegorz Michał_1": 45,
            "HOŁOWNIA Szymon Franciszek_1": 58,
            "JAKUBIAK Marek_1": 13,
            "MACIAK Maciej_1": 2,
            "MENTZEN Sławomir Jerzy_1": 121,
            "NAWROCKI Karol Tadeusz_1": 287,
            "SENYSZYN Joanna_1": 17,
            "STANOWSKI Krzysztof Jakub_1": 34,
            "TRZASKOWSKI Rafał Kazimierz_1": 657,
            "WOCH Marek Marian_1": 2,
            "ZANDBERG Adrian Tadeusz_1": 88
        },
        "second_round": {
            "eligible_voters_2": 1731,
            "issued_2": 1473,
            "turnout_2": 85.1,
            "NAWROCKI Karol Tadeusz_2": 469,
            "TRZASKOWSKI Rafał Kazimierz_2": 992
        },
        "calculations": {
            "issued_scale": 1.038787023977433,
            "change_TRZASKOWSKI Rafał Kazimierz": 0.5099,
            "change_NAWROCKI Karol Tadeusz": 0.6341,
            "expected_nawrocki": 510.14,
            "expected_trzaskowski": 936.89,
            "delta_nawrocki": -41.144152327221434,
            "delta_trzaskowski": 55.11382792665722,
            "diff_pct_nawrocki": -0.0807,
            "delta_from_median_change": -0.1847,
            "delta_from_median_difference": -0.0849,
            "alert_index": 0.0806,
            "change_TRZASKOWSKI Rafał Kazimierz_pct": 50.99,
            "change_NAWROCKI Karol Tadeusz_pct": 63.41,
            "diff_pct_nawrocki_pct": -8.07,
            "delta_from_median_change_pct": -18.47,
            "delta_from_median_difference_pct": -8.49,
            "alert_index_pct": 8.06
        },
        "alert_index_pct": 0.0806,
        "alert_index": 0.0806
    },
    {
        "commission": {
            "Nr komisji": "5",
            "Gmina": "m. Bielsk Podlaski",
            "Teryt Gminy": "200301",
            "Powiat": "bielski",
            "Teryt Powiatu": "200300",
            "Województwo": "podlaskie",
            "Siedziba": "Szkoła Podstawowa Nr 4 im. Adama Mickiewicza (wejście od ul. Widowskiej), ul. Adama Mickiewicza 126, 17-100 Bielsk Podlaski",
            "Typ obwodu": "stały",
            "Typ obszaru": "miasto",
            "id": "1c5415d5c6c701a9f172360afa8cedb5"
        },
        "turnout": {
            "first": "59.39% (1015 z 1709)",
            "second": "64.65% (1090 z 1686)",
            "scale": 1.0885670988381884
        },
        "first_round": {
            "eligible_voters_1": 1709,
            "issued_1": 1015,
            "turnout_1": 59.39,
            "BARTOSZEWICZ Artur_1": 3,
            "BIEJAT Magdalena Agnieszka_1": 51,
            "BRAUN Grzegorz Michał_1": 88,
            "HOŁOWNIA Szymon Franciszek_1": 69,
            "JAKUBIAK Marek_1": 1,
            "MACIAK Maciej_1": 11,
            "MENTZEN Sławomir Jerzy_1": 136,
            "NAWROCKI Karol Tadeusz_1": 258,
            "SENYSZYN Joanna_1": 8,
            "STANOWSKI Krzysztof Jakub_1": 5,
            "TRZASKOWSKI Rafał Kazimierz_1": 348,
            "WOCH Marek Marian_1": 0,
            "ZANDBERG Adrian Tadeusz_1": 35
        },
        "second_round": {
            "eligible_voters_2": 1686,
            "issued_2": 1090,
            "turnout_2": 64.65,
            "NAWROCKI Karol Tadeusz_2": 479,
            "TRZASKOWSKI Rafał Kazimierz_2": 599
        },
        "calculations": {
            "issued_scale": 1.0738916256157636,
            "change_TRZASKOWSKI Rafał Kazimierz": 0.7213,
            "change_NAWROCKI Karol Tadeusz": 0.8566,
            "expected_nawrocki": 521,
            "expected_trzaskowski": 550.74,
            "delta_nawrocki": -42.00066995073894,
            "delta_trzaskowski": 48.256827586206896,
            "diff_pct_nawrocki": -0.0806,
            "delta_from_median_change": 0.0378,
            "delta_from_median_difference": -0.0848,
            "alert_index": 0.0806,
            "change_TRZASKOWSKI Rafał Kazimierz_pct": 72.13,
            "change_NAWROCKI Karol Tadeusz_pct": 85.66,
            "diff_pct_nawrocki_pct": -8.06,
            "delta_from_median_change_pct": 3.78,
            "delta_from_median_difference_pct": -8.48,
            "alert_index_pct": 8.06
        },
        "alert_index_pct": 0.0806,
        "alert_index": 0.0806
    }
]