[
    {
        "commission": {
            "Nr komisji": "5",
            "Gmina": "gm. Puławy",
            "Teryt Gminy": "61409",
            "Powiat": "puławski",
            "Teryt Powiatu": "61400",
            "Województwo": "lubelskie",
            "Siedziba": "Szkoła Podstawowa, Borowa 9A, 24-100 Puławy",
            "Typ obwodu": "stały",
            "Typ obszaru": "wieś",
            "id": "43686452c5b18ef5e757755edf27c412"
        },
        "turnout": {
            "first": "63.5% (381 z 600)",
            "second": "65.17% (393 z 603)",
            "scale": 1.0262992125984252
        },
        "first_round": {
            "eligible_voters_1": 600,
            "issued_1": 381,
            "turnout_1": 63.5,
            "BARTOSZEWICZ Artur_1": 2,
            "BIEJAT Magdalena Agnieszka_1": 10,
            "BRAUN Grzegorz Michał_1": 15,
            "HOŁOWNIA Szymon Franciszek_1": 14,
            "JAKUBIAK Marek_1": 5,
            "MACIAK Maciej_1": 1,
            "MENTZEN Sławomir Jerzy_1": 59,
            "NAWROCKI Karol Tadeusz_1": 183,
            "SENYSZYN Joanna_1": 1,
            "STANOWSKI Krzysztof Jakub_1": 5,
            "TRZASKOWSKI Rafał Kazimierz_1": 71,
            "WOCH Marek Marian_1": 0,
            "ZANDBERG Adrian Tadeusz_1": 15
        },
        "second_round": {
            "eligible_voters_2": 603,
            "issued_2": 393,
            "turnout_2": 65.17,
            "NAWROCKI Karol Tadeusz_2": 271,
            "TRZASKOWSKI Rafał Kazimierz_2": 119
        },
        "calculations": {
            "issued_scale": 1.031496062992126,
            "change_TRZASKOWSKI Rafał Kazimierz": 0.6761,
            "change_NAWROCKI Karol Tadeusz": 0.4809,
            "expected_nawrocki": 264.45,
            "expected_trzaskowski": 120.3,
            "delta_nawrocki": 6.551228346456696,
            "delta_trzaskowski": -1.2992598425196888,
            "diff_pct_nawrocki": 0.0248,
            "delta_from_median_change": -0.3379,
            "delta_from_median_difference": 0.0206,
            "alert_index": 0.0248,
            "change_TRZASKOWSKI Rafał Kazimierz_pct": 67.61,
            "change_NAWROCKI Karol Tadeusz_pct": 48.09,
            "diff_pct_nawrocki_pct": 2.48,
            "delta_from_median_change_pct": -33.79,
            "delta_from_median_difference_pct": 2.06,
            "alert_index_pct": 2.48
        },
        "alert_index_pct": 0.0248,
        "alert_index": 0.0248
    },
    {
        "commission": {
            "Nr komisji": "5",
            "Gmina": "gm. Lubycza Królewska",
            "Teryt Gminy": "61805",
            "Powiat": "tomaszowski",
            "Teryt Powiatu": "61800",
            "Województwo": "lubelskie",
            "Siedziba": "Wiejski Dom Kultury, Żurawce ul. Szkolna 7, 22-680 Lubycza Królewska",
            "Typ obwodu": "stały",
            "Typ obszaru": "wieś",
            "id": "b522abcf15cbb3d82047f47418d322f4"
        },
        "turnout": {
            "first": "54.02% (141 z 261)",
            "second": "55.56% (145 z 261)",
            "scale": 1.0285079600148093
        },
        "first_round": {
            "eligible_voters_1": 261,
            "issued_1": 141,
            "turnout_1": 54.02,
            "BARTOSZEWICZ Artur_1": 1,
            "BIEJAT Magdalena Agnieszka_1": 1,
            "BRAUN Grzegorz Michał_1": 12,
            "HOŁOWNIA Szymon Franciszek_1": 5,
            "JAKUBIAK Marek_1": 2,
            "MACIAK Maciej_1": 0,
            "MENTZEN Sławomir Jerzy_1": 27,
            "NAWROCKI Karol Tadeusz_1": 60,
            "SENYSZYN Joanna_1": 3,
            "STANOWSKI Krzysztof Jakub_1": 0,
            "TRZASKOWSKI Rafał Kazimierz_1": 26,
            "WOCH Marek Marian_1": 0,
            "ZANDBERG Adrian Tadeusz_1": 4
        },
        "second_round": {
            "eligible_voters_2": 261,
            "issued_2": 145,
            "turnout_2": 55.56,
            "NAWROCKI Karol Tadeusz_2": 97,
            "TRZASKOWSKI Rafał Kazimierz_2": 47
        },
        "calculations": {
            "issued_scale": 1.0283687943262412,
            "change_TRZASKOWSKI Rafał Kazimierz": 0.8077,
            "change_NAWROCKI Karol Tadeusz": 0.6167,
            "expected_nawrocki": 99.47,
            "expected_trzaskowski": 42.44,
            "delta_nawrocki": -2.4741134751773046,
            "delta_trzaskowski": 4.559219858156034,
            "diff_pct_nawrocki": -0.0249,
            "delta_from_median_change": -0.2021,
            "delta_from_median_difference": -0.0291,
            "alert_index": 0.0248,
            "change_TRZASKOWSKI Rafał Kazimierz_pct": 80.77,
            "change_NAWROCKI Karol Tadeusz_pct": 61.67,
            "diff_pct_nawrocki_pct": -2.49,
            "delta_from_median_change_pct": -20.21,
            "delta_from_median_difference_pct": -2.91,
            "alert_index_pct": 2.48
        },
        "alert_index_pct": 0.0248,
        "alert_index": 0.0248
    },
    {
        "commission": {
            "Nr komisji": "58",
            "Gmina": "m. Lublin",
            "Teryt Gminy": "66301",
            "Powiat": "Lublin",
            "Teryt Powiatu": "66300",
            "Województwo": "lubelskie",
            "Siedziba": "Przedszkole Niepubliczne Akademia Poziomkowa w Lublinie, ul. Siewna 20, 20-617 Lublin",
            "Typ obwodu": "stały",
            "Typ obszaru": "miasto",
            "id": "75985a8642c99dc8278bca2fc273723b"
        },
        "turnout": {
            "first": "67.49% (816 z 1209)",
            "second": "71.15% (888 z 1248)",
            "scale": 1.0542302563342718
        },
        "first_round": {
            "eligible_voters_1": 1209,
            "issued_1": 816,
            "turnout_1": 67.49,
            "BARTOSZEWICZ Artur_1": 3,
            "BIEJAT Magdalena Agnieszka_1": 32,
            "BRAUN Grzegorz Michał_1": 53,
            "HOŁOWNIA Szymon Franciszek_1": 31,
            "JAKUBIAK Marek_1": 13,
            "MACIAK Maciej_1": 3,
            "MENTZEN Sławomir Jerzy_1": 88,
            "NAWROCKI Karol Tadeusz_1": 239,
            "SENYSZYN Joanna_1": 2,
            "STANOWSKI Krzysztof Jakub_1": 13,
            "TRZASKOWSKI Rafał Kazimierz_1": 259,
            "WOCH Marek Marian_1": 0,
            "ZANDBERG Adrian Tadeusz_1": 80
        },
        "second_round": {
            "eligible_voters_2": 1248,
            "issued_2": 888,
            "turnout_2": 71.15,
            "NAWROCKI Karol Tadeusz_2": 418,
            "TRZASKOWSKI Rafał Kazimierz_2": 466
        },
        "calculations": {
            "issued_scale": 1.088235294117647,
            "change_TRZASKOWSKI Rafał Kazimierz": 0.7992,
            "change_NAWROCKI Karol Tadeusz": 0.749,
            "expected_nawrocki": 428.63,
            "expected_trzaskowski": 438.69,
            "delta_nawrocki": -10.631941176470605,
            "delta_trzaskowski": 27.30841176470591,
            "diff_pct_nawrocki": -0.0248,
            "delta_from_median_change": -0.0698,
            "delta_from_median_difference": -0.029,
            "alert_index": 0.0248,
            "change_TRZASKOWSKI Rafał Kazimierz_pct": 79.92,
            "change_NAWROCKI Karol Tadeusz_pct": 74.9,
            "diff_pct_nawrocki_pct": -2.48,
            "delta_from_median_change_pct": -6.98,
            "delta_from_median_difference_pct": -2.9,
            "alert_index_pct": 2.48
        },
        "alert_index_pct": 0.0248,
        "alert_index": 0.0248
    },
    {
        "commission": {
            "Nr komisji": "6",
            "Gmina": "gm. Drzewica",
            "Teryt Gminy": "100702",
            "Powiat": "opoczyński",
            "Teryt Powiatu": "100700",
            "Województwo": "łódzkie",
            "Siedziba": "Szkoła Podstawowa w Brzustowcu, Brzustowiec 152, 26-340 Drzewica",
            "Typ obwodu": "stały",
            "Typ obszaru": "wieś",
            "id": "9a4705d630a10f744b105da6f115450e"
        },
        "turnout": {
            "first": "67.59% (367 z 543)",
            "second": "75.42% (408 z 541)",
            "scale": 1.1158455392809588
        },
        "first_round": {
            "eligible_voters_1": 543,
            "issued_1": 367,
            "turnout_1": 67.59,
            "BARTOSZEWICZ Artur_1": 1,
            "BIEJAT Magdalena Agnieszka_1": 9,
            "BRAUN Grzegorz Michał_1": 25,
            "HOŁOWNIA Szymon Franciszek_1": 11,
            "JAKUBIAK Marek_1": 6,
            "MACIAK Maciej_1": 2,
            "MENTZEN Sławomir Jerzy_1": 55,
            "NAWROCKI Karol Tadeusz_1": 215,
            "SENYSZYN Joanna_1": 2,
            "STANOWSKI Krzysztof Jakub_1": 1,
            "TRZASKOWSKI Rafał Kazimierz_1": 32,
            "WOCH Marek Marian_1": 1,
            "ZANDBERG Adrian Tadeusz_1": 6
        },
        "second_round": {
            "eligible_voters_2": 541,
            "issued_2": 408,
            "turnout_2": 75.42,
            "NAWROCKI Karol Tadeusz_2": 330,
            "TRZASKOWSKI Rafał Kazimierz_2": 74
        },
        "calculations": {
            "issued_scale": 1.111716621253406,
            "change_TRZASKOWSKI Rafał Kazimierz": 1.3125,
            "change_NAWROCKI Karol Tadeusz": 0.5349,
            "expected_nawrocki": 322.02,
            "expected_trzaskowski": 73.75,
            "delta_nawrocki": 7.983498637602224,
            "delta_trzaskowski": 0.24538419618529872,
            "diff_pct_nawrocki": 0.0248,
            "delta_from_median_change": -0.2839,
            "delta_from_median_difference": 0.0206,
            "alert_index": 0.0248,
            "change_TRZASKOWSKI Rafał Kazimierz_pct": 131.25,
            "change_NAWROCKI Karol Tadeusz_pct": 53.49,
            "diff_pct_nawrocki_pct": 2.48,
            "delta_from_median_change_pct": -28.39,
            "delta_from_median_difference_pct": 2.06,
            "alert_index_pct": 2.48
        },
        "alert_index_pct": 0.0248,
        "alert_index": 0.0248
    },
    {
        "commission": {
            "Nr komisji": "9",
            "Gmina": "gm. Poddębice",
            "Teryt Gminy": "101103",
            "Powiat": "poddębicki",
            "Teryt Powiatu": "101100",
            "Województwo": "łódzkie",
            "Siedziba": "Budynek OSP w Panaszewie, Panaszew 24A, 99-200 Poddębice",
            "Typ obwodu": "stały",
            "Typ obszaru": "wieś",
            "id": "312964a2c083723a62f60bf204b4ccf2"
        },
        "turnout": {
            "first": "62.24% (300 z 482)",
            "second": "67.79% (322 z 475)",
            "scale": 1.0891709511568124
        },
        "first_round": {
            "eligible_voters_1": 482,
            "issued_1": 300,
            "turnout_1": 62.24,
            "BARTOSZEWICZ Artur_1": 0,
            "BIEJAT Magdalena Agnieszka_1": 17,
            "BRAUN Grzegorz Michał_1": 21,
            "HOŁOWNIA Szymon Franciszek_1": 14,
            "JAKUBIAK Marek_1": 1,
            "MACIAK Maciej_1": 0,
            "MENTZEN Sławomir Jerzy_1": 43,
            "NAWROCKI Karol Tadeusz_1": 103,
            "SENYSZYN Joanna_1": 2,
            "STANOWSKI Krzysztof Jakub_1": 7,
            "TRZASKOWSKI Rafał Kazimierz_1": 75,
            "WOCH Marek Marian_1": 2,
            "ZANDBERG Adrian Tadeusz_1": 13
        },
        "second_round": {
            "eligible_voters_2": 475,
            "issued_2": 322,
            "turnout_2": 67.79,
            "NAWROCKI Karol Tadeusz_2": 187,
            "TRZASKOWSKI Rafał Kazimierz_2": 131
        },
        "calculations": {
            "issued_scale": 1.0733333333333333,
            "change_TRZASKOWSKI Rafał Kazimierz": 0.7467,
            "change_NAWROCKI Karol Tadeusz": 0.8155,
            "expected_nawrocki": 182.47,
            "expected_trzaskowski": 134.16,
            "delta_nawrocki": 4.530113333333361,
            "delta_trzaskowski": -3.1634466666666583,
            "diff_pct_nawrocki": 0.0248,
            "delta_from_median_change": -0.0033,
            "delta_from_median_difference": 0.0206,
            "alert_index": 0.0248,
            "change_TRZASKOWSKI Rafał Kazimierz_pct": 74.67,
            "change_NAWROCKI Karol Tadeusz_pct": 81.55,
            "diff_pct_nawrocki_pct": 2.48,
            "delta_from_median_change_pct": -0.33,
            "delta_from_median_difference_pct": 2.06,
            "alert_index_pct": 2.48
        },
        "alert_index_pct": 0.0248,
        "alert_index": 0.0248
    },
    {
        "commission": {
            "Nr komisji": "1",
            "Gmina": "gm. Liszki",
            "Teryt Gminy": "120607",
            "Powiat": "krakowski",
            "Teryt Powiatu": "120600",
            "Województwo": "małopolskie",
            "Siedziba": "GOPS w Liszkach, ul. Św. Jana Kantego 5, 32-060 Liszki",
            "Typ obwodu": "stały",
            "Typ obszaru": "wieś",
            "id": "f976d4941c11436a3211a9c51f92fc7c"
        },
        "turnout": {
            "first": "70.5% (1054 z 1495)",
            "second": "73.82% (1097 z 1486)",
            "scale": 1.0470921985815602
        },
        "first_round": {
            "eligible_voters_1": 1495,
            "issued_1": 1054,
            "turnout_1": 70.5,
            "BARTOSZEWICZ Artur_1": 3,
            "BIEJAT Magdalena Agnieszka_1": 21,
            "BRAUN Grzegorz Michał_1": 71,
            "HOŁOWNIA Szymon Franciszek_1": 58,
            "JAKUBIAK Marek_1": 21,
            "MACIAK Maciej_1": 1,
            "MENTZEN Sławomir Jerzy_1": 174,
            "NAWROCKI Karol Tadeusz_1": 469,
            "SENYSZYN Joanna_1": 12,
            "STANOWSKI Krzysztof Jakub_1": 13,
            "TRZASKOWSKI Rafał Kazimierz_1": 155,
            "WOCH Marek Marian_1": 0,
            "ZANDBERG Adrian Tadeusz_1": 51
        },
        "second_round": {
            "eligible_voters_2": 1486,
            "issued_2": 1097,
            "turnout_2": 73.82,
            "NAWROCKI Karol Tadeusz_2": 761,
            "TRZASKOWSKI Rafał Kazimierz_2": 329
        },
        "calculations": {
            "issued_scale": 1.040796963946869,
            "change_TRZASKOWSKI Rafał Kazimierz": 1.1226,
            "change_NAWROCKI Karol Tadeusz": 0.6226,
            "expected_nawrocki": 742.59,
            "expected_trzaskowski": 323.18,
            "delta_nawrocki": 18.408018975332197,
            "delta_trzaskowski": 5.815889943074069,
            "diff_pct_nawrocki": 0.0248,
            "delta_from_median_change": -0.1962,
            "delta_from_median_difference": 0.0206,
            "alert_index": 0.0248,
            "change_TRZASKOWSKI Rafał Kazimierz_pct": 112.26,
            "change_NAWROCKI Karol Tadeusz_pct": 62.26,
            "diff_pct_nawrocki_pct": 2.48,
            "delta_from_median_change_pct": -19.62,
            "delta_from_median_difference_pct": 2.06,
            "alert_index_pct": 2.48
        },
        "alert_index_pct": 0.0248,
        "alert_index": 0.0248
    },
    {
        "commission": {
            "Nr komisji": "14",
            "Gmina": "gm. Chełmiec",
            "Teryt Gminy": "121002",
            "Powiat": "nowosądecki",
            "Teryt Powiatu": "121000",
            "Województwo": "małopolskie",
            "Siedziba": "Szkoła Podstawowa, Januszowa 5, 33-300 Nowy Sącz",
            "Typ obwodu": "stały",
            "Typ obszaru": "wieś",
            "id": "e29904170c814a45c45cbf2afdfa1f83"
        },
        "turnout": {
            "first": "72.82% (359 z 493)",
            "second": "75.79% (360 z 475)",
            "scale": 1.0407854984894263
        },
        "first_round": {
            "eligible_voters_1": 493,
            "issued_1": 359,
            "turnout_1": 72.82,
            "BARTOSZEWICZ Artur_1": 4,
            "BIEJAT Magdalena Agnieszka_1": 3,
            "BRAUN Grzegorz Michał_1": 19,
            "HOŁOWNIA Szymon Franciszek_1": 8,
            "JAKUBIAK Marek_1": 2,
            "MACIAK Maciej_1": 0,
            "MENTZEN Sławomir Jerzy_1": 84,
            "NAWROCKI Karol Tadeusz_1": 205,
            "SENYSZYN Joanna_1": 2,
            "STANOWSKI Krzysztof Jakub_1": 0,
            "TRZASKOWSKI Rafał Kazimierz_1": 20,
            "WOCH Marek Marian_1": 0,
            "ZANDBERG Adrian Tadeusz_1": 10
        },
        "second_round": {
            "eligible_voters_2": 475,
            "issued_2": 360,
            "turnout_2": 75.79,
            "NAWROCKI Karol Tadeusz_2": 307,
            "TRZASKOWSKI Rafał Kazimierz_2": 52
        },
        "calculations": {
            "issued_scale": 1.0027855153203342,
            "change_TRZASKOWSKI Rafał Kazimierz": 1.6,
            "change_NAWROCKI Karol Tadeusz": 0.4976,
            "expected_nawrocki": 299.57,
            "expected_trzaskowski": 52.41,
            "delta_nawrocki": 7.427855153203325,
            "delta_trzaskowski": -0.40557103064066524,
            "diff_pct_nawrocki": 0.0248,
            "delta_from_median_change": -0.3212,
            "delta_from_median_difference": 0.0206,
            "alert_index": 0.0248,
            "change_TRZASKOWSKI Rafał Kazimierz_pct": 160,
            "change_NAWROCKI Karol Tadeusz_pct": 49.76,
            "diff_pct_nawrocki_pct": 2.48,
            "delta_from_median_change_pct": -32.12,
            "delta_from_median_difference_pct": 2.06,
            "alert_index_pct": 2.48
        },
        "alert_index_pct": 0.0248,
        "alert_index": 0.0248
    },
    {
        "commission": {
            "Nr komisji": "12",
            "Gmina": "gm. Czarny Dunajec",
            "Teryt Gminy": "121103",
            "Powiat": "nowotarski",
            "Teryt Powiatu": "121100",
            "Województwo": "małopolskie",
            "Siedziba": "Remiza OSP, Podczerwone 112, 34-470 Czarny Dunajec",
            "Typ obwodu": "stały",
            "Typ obszaru": "wieś",
            "id": "f4257e274a9c0b26e484adcff82c658c"
        },
        "turnout": {
            "first": "45.27% (349 z 771)",
            "second": "47.56% (361 z 759)",
            "scale": 1.0505853766291142
        },
        "first_round": {
            "eligible_voters_1": 771,
            "issued_1": 349,
            "turnout_1": 45.27,
            "BARTOSZEWICZ Artur_1": 1,
            "BIEJAT Magdalena Agnieszka_1": 2,
            "BRAUN Grzegorz Michał_1": 39,
            "HOŁOWNIA Szymon Franciszek_1": 10,
            "JAKUBIAK Marek_1": 1,
            "MACIAK Maciej_1": 0,
            "MENTZEN Sławomir Jerzy_1": 67,
            "NAWROCKI Karol Tadeusz_1": 193,
            "SENYSZYN Joanna_1": 1,
            "STANOWSKI Krzysztof Jakub_1": 0,
            "TRZASKOWSKI Rafał Kazimierz_1": 28,
            "WOCH Marek Marian_1": 0,
            "ZANDBERG Adrian Tadeusz_1": 5
        },
        "second_round": {
            "eligible_voters_2": 759,
            "issued_2": 361,
            "turnout_2": 47.56,
            "NAWROCKI Karol Tadeusz_2": 307,
            "TRZASKOWSKI Rafał Kazimierz_2": 50
        },
        "calculations": {
            "issued_scale": 1.0343839541547277,
            "change_TRZASKOWSKI Rafał Kazimierz": 0.7857,
            "change_NAWROCKI Karol Tadeusz": 0.5907,
            "expected_nawrocki": 299.56,
            "expected_trzaskowski": 57.3,
            "delta_nawrocki": 7.436200573065946,
            "delta_trzaskowski": -7.298664756446982,
            "diff_pct_nawrocki": 0.0248,
            "delta_from_median_change": -0.2281,
            "delta_from_median_difference": 0.0206,
            "alert_index": 0.0248,
            "change_TRZASKOWSKI Rafał Kazimierz_pct": 78.57,
            "change_NAWROCKI Karol Tadeusz_pct": 59.07,
            "diff_pct_nawrocki_pct": 2.48,
            "delta_from_median_change_pct": -22.81,
            "delta_from_median_difference_pct": 2.06,
            "alert_index_pct": 2.48
        },
        "alert_index_pct": 0.0248,
        "alert_index": 0.0248
    },
    {
        "commission": {
            "Nr komisji": "9",
            "Gmina": "gm. Andrychów",
            "Teryt Gminy": "121801",
            "Powiat": "wadowicki",
            "Teryt Powiatu": "121800",
            "Województwo": "małopolskie",
            "Siedziba": "Andrychów, Szkoła Podstawowa Nr 5, sala lekcyjna, ul. Stanisława Lenartowicza 26, 34-120 Andrychów",
            "Typ obwodu": "stały",
            "Typ obszaru": "miasto",
            "id": "b4e787cd514535d1c366c7461d2da196"
        },
        "turnout": {
            "first": "67.74% (863 z 1274)",
            "second": "71.08% (892 z 1255)",
            "scale": 1.0493061706524949
        },
        "first_round": {
            "eligible_voters_1": 1274,
            "issued_1": 863,
            "turnout_1": 67.74,
            "BARTOSZEWICZ Artur_1": 1,
            "BIEJAT Magdalena Agnieszka_1": 26,
            "BRAUN Grzegorz Michał_1": 73,
            "HOŁOWNIA Szymon Franciszek_1": 49,
            "JAKUBIAK Marek_1": 10,
            "MACIAK Maciej_1": 1,
            "MENTZEN Sławomir Jerzy_1": 130,
            "NAWROCKI Karol Tadeusz_1": 272,
            "SENYSZYN Joanna_1": 4,
            "STANOWSKI Krzysztof Jakub_1": 19,
            "TRZASKOWSKI Rafał Kazimierz_1": 250,
            "WOCH Marek Marian_1": 0,
            "ZANDBERG Adrian Tadeusz_1": 23
        },
        "second_round": {
            "eligible_voters_2": 1255,
            "issued_2": 892,
            "turnout_2": 71.08,
            "NAWROCKI Karol Tadeusz_2": 482,
            "TRZASKOWSKI Rafał Kazimierz_2": 400
        },
        "calculations": {
            "issued_scale": 1.033603707995365,
            "change_TRZASKOWSKI Rafał Kazimierz": 0.6,
            "change_NAWROCKI Karol Tadeusz": 0.7721,
            "expected_nawrocki": 494.24,
            "expected_trzaskowski": 380.19,
            "delta_nawrocki": -12.239318655851775,
            "delta_trzaskowski": 19.81058169177288,
            "diff_pct_nawrocki": -0.0248,
            "delta_from_median_change": -0.0467,
            "delta_from_median_difference": -0.029,
            "alert_index": 0.0248,
            "change_TRZASKOWSKI Rafał Kazimierz_pct": 60,
            "change_NAWROCKI Karol Tadeusz_pct": 77.21,
            "diff_pct_nawrocki_pct": -2.48,
            "delta_from_median_change_pct": -4.67,
            "delta_from_median_difference_pct": -2.9,
            "alert_index_pct": 2.48
        },
        "alert_index_pct": 0.0248,
        "alert_index": 0.0248
    },
    {
        "commission": {
            "Nr komisji": "300",
            "Gmina": "m. Kraków",
            "Teryt Gminy": "126101",
            "Powiat": "Kraków",
            "Teryt Powiatu": "126100",
            "Województwo": "małopolskie",
            "Siedziba": "Szkoła Podstawowa Nr 155, os. Osiedle 2 Pułku Lotniczego 21, 31-869 Kraków",
            "Typ obwodu": "stały",
            "Typ obszaru": "miasto",
            "id": "2cdf379268a6280f1c9ba3bbf4546c0c"
        },
        "turnout": {
            "first": "70.72% (1140 z 1612)",
            "second": "77.76% (1220 z 1569)",
            "scale": 1.0995475113122173
        },
        "first_round": {
            "eligible_voters_1": 1612,
            "issued_1": 1140,
            "turnout_1": 70.72,
            "BARTOSZEWICZ Artur_1": 3,
            "BIEJAT Magdalena Agnieszka_1": 60,
            "BRAUN Grzegorz Michał_1": 41,
            "HOŁOWNIA Szymon Franciszek_1": 68,
            "JAKUBIAK Marek_1": 8,
            "MACIAK Maciej_1": 0,
            "MENTZEN Sławomir Jerzy_1": 130,
            "NAWROCKI Karol Tadeusz_1": 293,
            "SENYSZYN Joanna_1": 10,
            "STANOWSKI Krzysztof Jakub_1": 10,
            "TRZASKOWSKI Rafał Kazimierz_1": 425,
            "WOCH Marek Marian_1": 0,
            "ZANDBERG Adrian Tadeusz_1": 92
        },
        "second_round": {
            "eligible_voters_2": 1569,
            "issued_2": 1220,
            "turnout_2": 77.76,
            "NAWROCKI Karol Tadeusz_2": 506,
            "TRZASKOWSKI Rafał Kazimierz_2": 709
        },
        "calculations": {
            "issued_scale": 1.0701754385964912,
            "change_TRZASKOWSKI Rafał Kazimierz": 0.6682,
            "change_NAWROCKI Karol Tadeusz": 0.727,
            "expected_nawrocki": 518.86,
            "expected_trzaskowski": 689.37,
            "delta_nawrocki": -12.855298245613994,
            "delta_trzaskowski": 19.62722807017542,
            "diff_pct_nawrocki": -0.0248,
            "delta_from_median_change": -0.0918,
            "delta_from_median_difference": -0.029,
            "alert_index": 0.0248,
            "change_TRZASKOWSKI Rafał Kazimierz_pct": 66.82,
            "change_NAWROCKI Karol Tadeusz_pct": 72.7,
            "diff_pct_nawrocki_pct": -2.48,
            "delta_from_median_change_pct": -9.18,
            "delta_from_median_difference_pct": -2.9,
            "alert_index_pct": 2.48
        },
        "alert_index_pct": 0.0248,
        "alert_index": 0.0248
    },
    {
        "commission": {
            "Nr komisji": "12",
            "Gmina": "m. Ostrów Mazowiecka",
            "Teryt Gminy": "141601",
            "Powiat": "ostrowski",
            "Teryt Powiatu": "141600",
            "Województwo": "mazowieckie",
            "Siedziba": "Liceum Ogólnokształcące im. Mikołaja Kopernika, ul. Tadeusza Kościuszki 36, 07-300 Ostrów Mazowiecka",
            "Typ obwodu": "stały",
            "Typ obszaru": "miasto",
            "id": "36931b926c81e261707b2c745b471867"
        },
        "turnout": {
            "first": "63.08% (863 z 1368)",
            "second": "68.27% (910 z 1333)",
            "scale": 1.082276474318326
        },
        "first_round": {
            "eligible_voters_1": 1368,
            "issued_1": 863,
            "turnout_1": 63.08,
            "BARTOSZEWICZ Artur_1": 2,
            "BIEJAT Magdalena Agnieszka_1": 24,
            "BRAUN Grzegorz Michał_1": 43,
            "HOŁOWNIA Szymon Franciszek_1": 31,
            "JAKUBIAK Marek_1": 5,
            "MACIAK Maciej_1": 2,
            "MENTZEN Sławomir Jerzy_1": 102,
            "NAWROCKI Karol Tadeusz_1": 359,
            "SENYSZYN Joanna_1": 5,
            "STANOWSKI Krzysztof Jakub_1": 5,
            "TRZASKOWSKI Rafał Kazimierz_1": 260,
            "WOCH Marek Marian_1": 0,
            "ZANDBERG Adrian Tadeusz_1": 24
        },
        "second_round": {
            "eligible_voters_2": 1333,
            "issued_2": 910,
            "turnout_2": 68.27,
            "NAWROCKI Karol Tadeusz_2": 517,
            "TRZASKOWSKI Rafał Kazimierz_2": 384
        },
        "calculations": {
            "issued_scale": 1.0544611819235226,
            "change_TRZASKOWSKI Rafał Kazimierz": 0.4769,
            "change_NAWROCKI Karol Tadeusz": 0.4401,
            "expected_nawrocki": 530.13,
            "expected_trzaskowski": 369.33,
            "delta_nawrocki": -13.12719582850525,
            "delta_trzaskowski": 14.67180764774048,
            "diff_pct_nawrocki": -0.0248,
            "delta_from_median_change": -0.3787,
            "delta_from_median_difference": -0.029,
            "alert_index": 0.0248,
            "change_TRZASKOWSKI Rafał Kazimierz_pct": 47.69,
            "change_NAWROCKI Karol Tadeusz_pct": 44.01,
            "diff_pct_nawrocki_pct": -2.48,
            "delta_from_median_change_pct": -37.87,
            "delta_from_median_difference_pct": -2.9,
            "alert_index_pct": 2.48
        },
        "alert_index_pct": 0.0248,
        "alert_index": 0.0248
    },
    {
        "commission": {
            "Nr komisji": "12",
            "Gmina": "m. Przasnysz",
            "Teryt Gminy": "142201",
            "Powiat": "przasnyski",
            "Teryt Powiatu": "142200",
            "Województwo": "mazowieckie",
            "Siedziba": "Szkoła Podstawowa nr 3, ul. Orlika 48, 06-300 Przasnysz",
            "Typ obwodu": "stały",
            "Typ obszaru": "miasto",
            "id": "10ef898fb26f70e3ba8b96219412a3a0"
        },
        "turnout": {
            "first": "67.88% (917 z 1351)",
            "second": "73.68% (991 z 1345)",
            "scale": 1.0854449027695936
        },
        "first_round": {
            "eligible_voters_1": 1351,
            "issued_1": 917,
            "turnout_1": 67.88,
            "BARTOSZEWICZ Artur_1": 3,
            "BIEJAT Magdalena Agnieszka_1": 31,
            "BRAUN Grzegorz Michał_1": 45,
            "HOŁOWNIA Szymon Franciszek_1": 40,
            "JAKUBIAK Marek_1": 3,
            "MACIAK Maciej_1": 0,
            "MENTZEN Sławomir Jerzy_1": 128,
            "NAWROCKI Karol Tadeusz_1": 338,
            "SENYSZYN Joanna_1": 15,
            "STANOWSKI Krzysztof Jakub_1": 9,
            "TRZASKOWSKI Rafał Kazimierz_1": 271,
            "WOCH Marek Marian_1": 0,
            "ZANDBERG Adrian Tadeusz_1": 31
        },
        "second_round": {
            "eligible_voters_2": 1345,
            "issued_2": 991,
            "turnout_2": 73.68,
            "NAWROCKI Karol Tadeusz_2": 569,
            "TRZASKOWSKI Rafał Kazimierz_2": 412
        },
        "calculations": {
            "issued_scale": 1.0806979280261724,
            "change_TRZASKOWSKI Rafał Kazimierz": 0.5203,
            "change_NAWROCKI Karol Tadeusz": 0.6834,
            "expected_nawrocki": 555.22,
            "expected_trzaskowski": 426.05,
            "delta_nawrocki": 13.7806324972737,
            "delta_trzaskowski": -14.054351145038197,
            "diff_pct_nawrocki": 0.0248,
            "delta_from_median_change": -0.1354,
            "delta_from_median_difference": 0.0206,
            "alert_index": 0.0248,
            "change_TRZASKOWSKI Rafał Kazimierz_pct": 52.03,
            "change_NAWROCKI Karol Tadeusz_pct": 68.34,
            "diff_pct_nawrocki_pct": 2.48,
            "delta_from_median_change_pct": -13.54,
            "delta_from_median_difference_pct": 2.06,
            "alert_index_pct": 2.48
        },
        "alert_index_pct": 0.0248,
        "alert_index": 0.0248
    },
    {
        "commission": {
            "Nr komisji": "2",
            "Gmina": "gm. Jastrzębia",
            "Teryt Gminy": "142504",
            "Powiat": "radomski",
            "Teryt Powiatu": "142500",
            "Województwo": "mazowieckie",
            "Siedziba": "Zespół Szkolno-Przedszkolny w Jastrzębi, Jastrzębia 109, 26-631 Jastrzębia",
            "Typ obwodu": "stały",
            "Typ obszaru": "wieś",
            "id": "189a41e9ae77ea8099efab9ecd5c616f"
        },
        "turnout": {
            "first": "76.15% (348 z 457)",
            "second": "77.52% (338 z 436)",
            "scale": 1.0179908076165463
        },
        "first_round": {
            "eligible_voters_1": 457,
            "issued_1": 348,
            "turnout_1": 76.15,
            "BARTOSZEWICZ Artur_1": 2,
            "BIEJAT Magdalena Agnieszka_1": 5,
            "BRAUN Grzegorz Michał_1": 41,
            "HOŁOWNIA Szymon Franciszek_1": 18,
            "JAKUBIAK Marek_1": 6,
            "MACIAK Maciej_1": 0,
            "MENTZEN Sławomir Jerzy_1": 49,
            "NAWROCKI Karol Tadeusz_1": 152,
            "SENYSZYN Joanna_1": 4,
            "STANOWSKI Krzysztof Jakub_1": 2,
            "TRZASKOWSKI Rafał Kazimierz_1": 54,
            "WOCH Marek Marian_1": 1,
            "ZANDBERG Adrian Tadeusz_1": 11
        },
        "second_round": {
            "eligible_voters_2": 436,
            "issued_2": 338,
            "turnout_2": 77.52,
            "NAWROCKI Karol Tadeusz_2": 238,
            "TRZASKOWSKI Rafał Kazimierz_2": 100
        },
        "calculations": {
            "issued_scale": 0.9712643678160919,
            "change_TRZASKOWSKI Rafał Kazimierz": 0.8519,
            "change_NAWROCKI Karol Tadeusz": 0.5658,
            "expected_nawrocki": 232.24,
            "expected_trzaskowski": 94.11,
            "delta_nawrocki": 5.764862068965527,
            "delta_trzaskowski": 5.890310344827583,
            "diff_pct_nawrocki": 0.0248,
            "delta_from_median_change": -0.253,
            "delta_from_median_difference": 0.0206,
            "alert_index": 0.0248,
            "change_TRZASKOWSKI Rafał Kazimierz_pct": 85.19,
            "change_NAWROCKI Karol Tadeusz_pct": 56.58,
            "diff_pct_nawrocki_pct": 2.48,
            "delta_from_median_change_pct": -25.3,
            "delta_from_median_difference_pct": 2.06,
            "alert_index_pct": 2.48
        },
        "alert_index_pct": 0.0248,
        "alert_index": 0.0248
    },
    {
        "commission": {
            "Nr komisji": "11",
            "Gmina": "gm. Wyszków",
            "Teryt Gminy": "143505",
            "Powiat": "wyszkowski",
            "Teryt Powiatu": "143500",
            "Województwo": "mazowieckie",
            "Siedziba": "Szkoła Podstawowa nr 4 im. Obrońców Westerplatte (wejście A), ul. Generała Józefa Sowińskiego 55, 07-202 Wyszków",
            "Typ obwodu": "stały",
            "Typ obszaru": "miasto",
            "id": "3c2e85620abfcf0b70242cee192c4765"
        },
        "turnout": {
            "first": "59.68% (663 z 1111)",
            "second": "64.73% (714 z 1103)",
            "scale": 1.084617962466488
        },
        "first_round": {
            "eligible_voters_1": 1111,
            "issued_1": 663,
            "turnout_1": 59.68,
            "BARTOSZEWICZ Artur_1": 4,
            "BIEJAT Magdalena Agnieszka_1": 26,
            "BRAUN Grzegorz Michał_1": 44,
            "HOŁOWNIA Szymon Franciszek_1": 29,
            "JAKUBIAK Marek_1": 4,
            "MACIAK Maciej_1": 2,
            "MENTZEN Sławomir Jerzy_1": 98,
            "NAWROCKI Karol Tadeusz_1": 219,
            "SENYSZYN Joanna_1": 1,
            "STANOWSKI Krzysztof Jakub_1": 14,
            "TRZASKOWSKI Rafał Kazimierz_1": 190,
            "WOCH Marek Marian_1": 0,
            "ZANDBERG Adrian Tadeusz_1": 30
        },
        "second_round": {
            "eligible_voters_2": 1103,
            "issued_2": 714,
            "turnout_2": 64.73,
            "NAWROCKI Karol Tadeusz_2": 403,
            "TRZASKOWSKI Rafał Kazimierz_2": 307
        },
        "calculations": {
            "issued_scale": 1.0769230769230769,
            "change_TRZASKOWSKI Rafał Kazimierz": 0.6158,
            "change_NAWROCKI Karol Tadeusz": 0.8402,
            "expected_nawrocki": 393.26,
            "expected_trzaskowski": 307.81,
            "delta_nawrocki": 9.737846153846135,
            "delta_trzaskowski": -0.8147692307691727,
            "diff_pct_nawrocki": 0.0248,
            "delta_from_median_change": 0.0214,
            "delta_from_median_difference": 0.0206,
            "alert_index": 0.0248,
            "change_TRZASKOWSKI Rafał Kazimierz_pct": 61.58,
            "change_NAWROCKI Karol Tadeusz_pct": 84.02,
            "diff_pct_nawrocki_pct": 2.48,
            "delta_from_median_change_pct": 2.14,
            "delta_from_median_difference_pct": 2.06,
            "alert_index_pct": 2.48
        },
        "alert_index_pct": 0.0248,
        "alert_index": 0.0248
    },
    {
        "commission": {
            "Nr komisji": "3",
            "Gmina": "gm. Puszcza Mariańska",
            "Teryt Gminy": "143803",
            "Powiat": "żyrardowski",
            "Teryt Powiatu": "143800",
            "Województwo": "mazowieckie",
            "Siedziba": "Budynek gminny w Starym Łajszczewie, Stary Łajszczew 49A, 96-330 Puszcza Mariańska",
            "Typ obwodu": "stały",
            "Typ obszaru": "wieś",
            "id": "efb816f2a33313c6e9956fedf3e5089d"
        },
        "turnout": {
            "first": "63.9% (239 z 374)",
            "second": "68.03% (249 z 366)",
            "scale": 1.0646322378716746
        },
        "first_round": {
            "eligible_voters_1": 374,
            "issued_1": 239,
            "turnout_1": 63.9,
            "BARTOSZEWICZ Artur_1": 0,
            "BIEJAT Magdalena Agnieszka_1": 4,
            "BRAUN Grzegorz Michał_1": 31,
            "HOŁOWNIA Szymon Franciszek_1": 9,
            "JAKUBIAK Marek_1": 2,
            "MACIAK Maciej_1": 0,
            "MENTZEN Sławomir Jerzy_1": 47,
            "NAWROCKI Karol Tadeusz_1": 99,
            "SENYSZYN Joanna_1": 0,
            "STANOWSKI Krzysztof Jakub_1": 2,
            "TRZASKOWSKI Rafał Kazimierz_1": 39,
            "WOCH Marek Marian_1": 0,
            "ZANDBERG Adrian Tadeusz_1": 5
        },
        "second_round": {
            "eligible_voters_2": 366,
            "issued_2": 249,
            "turnout_2": 68.03,
            "NAWROCKI Karol Tadeusz_2": 175,
            "TRZASKOWSKI Rafał Kazimierz_2": 72
        },
        "calculations": {
            "issued_scale": 1.0418410041841004,
            "change_TRZASKOWSKI Rafał Kazimierz": 0.8462,
            "change_NAWROCKI Karol Tadeusz": 0.7677,
            "expected_nawrocki": 179.45,
            "expected_trzaskowski": 66.42,
            "delta_nawrocki": -4.453987447698751,
            "delta_trzaskowski": 5.5795104602510435,
            "diff_pct_nawrocki": -0.0248,
            "delta_from_median_change": -0.0511,
            "delta_from_median_difference": -0.029,
            "alert_index": 0.0248,
            "change_TRZASKOWSKI Rafał Kazimierz_pct": 84.62,
            "change_NAWROCKI Karol Tadeusz_pct": 76.77,
            "diff_pct_nawrocki_pct": -2.48,
            "delta_from_median_change_pct": -5.11,
            "delta_from_median_difference_pct": -2.9,
            "alert_index_pct": 2.48
        },
        "alert_index_pct": 0.0248,
        "alert_index": 0.0248
    },
    {
        "commission": {
            "Nr komisji": "233",
            "Gmina": "Ochota",
            "Teryt Gminy": "146506",
            "Powiat": "Warszawa",
            "Teryt Powiatu": "146501",
            "Województwo": "mazowieckie",
            "Siedziba": "Szkoła Podstawowa nr 264, ul. Walentego Skorochód-Majewskiego 17, 02-104 Warszawa",
            "Typ obwodu": "stały",
            "Typ obszaru": "dzielnica w m.st. Warszawa",
            "id": "7dd1061eaef9d681022d7cd8e1f8b52c"
        },
        "turnout": {
            "first": "75.05% (1089 z 1451)",
            "second": "78.28% (1128 z 1441)",
            "scale": 1.0430379746835443
        },
        "first_round": {
            "eligible_voters_1": 1451,
            "issued_1": 1089,
            "turnout_1": 75.05,
            "BARTOSZEWICZ Artur_1": 6,
            "BIEJAT Magdalena Agnieszka_1": 72,
            "BRAUN Grzegorz Michał_1": 41,
            "HOŁOWNIA Szymon Franciszek_1": 64,
            "JAKUBIAK Marek_1": 9,
            "MACIAK Maciej_1": 0,
            "MENTZEN Sławomir Jerzy_1": 107,
            "NAWROCKI Karol Tadeusz_1": 280,
            "SENYSZYN Joanna_1": 23,
            "STANOWSKI Krzysztof Jakub_1": 13,
            "TRZASKOWSKI Rafał Kazimierz_1": 372,
            "WOCH Marek Marian_1": 0,
            "ZANDBERG Adrian Tadeusz_1": 96
        },
        "second_round": {
            "eligible_voters_2": 1441,
            "issued_2": 1128,
            "turnout_2": 78.28,
            "NAWROCKI Karol Tadeusz_2": 461,
            "TRZASKOWSKI Rafał Kazimierz_2": 650
        },
        "calculations": {
            "issued_scale": 1.0358126721763086,
            "change_TRZASKOWSKI Rafał Kazimierz": 0.7473,
            "change_NAWROCKI Karol Tadeusz": 0.6464,
            "expected_nawrocki": 472.74,
            "expected_trzaskowski": 633.51,
            "delta_nawrocki": -11.739724517906382,
            "delta_trzaskowski": 16.49179063360873,
            "diff_pct_nawrocki": -0.0248,
            "delta_from_median_change": -0.1724,
            "delta_from_median_difference": -0.029,
            "alert_index": 0.0248,
            "change_TRZASKOWSKI Rafał Kazimierz_pct": 74.73,
            "change_NAWROCKI Karol Tadeusz_pct": 64.64,
            "diff_pct_nawrocki_pct": -2.48,
            "delta_from_median_change_pct": -17.24,
            "delta_from_median_difference_pct": -2.9,
            "alert_index_pct": 2.48
        },
        "alert_index_pct": 0.0248,
        "alert_index": 0.0248
    },
    {
        "commission": {
            "Nr komisji": "14",
            "Gmina": "gm. Grodków",
            "Teryt Gminy": "160103",
            "Powiat": "brzeski",
            "Teryt Powiatu": "160100",
            "Województwo": "opolskie",
            "Siedziba": "Publiczna Szkoła Podstawowa, Gnojna 119, 49-200 Grodków",
            "Typ obwodu": "stały",
            "Typ obszaru": "wieś",
            "id": "8b21ff392b980ef6abefa58bfadb882d"
        },
        "turnout": {
            "first": "54.49% (328 z 602)",
            "second": "63.68% (377 z 592)",
            "scale": 1.1686547990456964
        },
        "first_round": {
            "eligible_voters_1": 602,
            "issued_1": 328,
            "turnout_1": 54.49,
            "BARTOSZEWICZ Artur_1": 3,
            "BIEJAT Magdalena Agnieszka_1": 6,
            "BRAUN Grzegorz Michał_1": 30,
            "HOŁOWNIA Szymon Franciszek_1": 6,
            "JAKUBIAK Marek_1": 3,
            "MACIAK Maciej_1": 0,
            "MENTZEN Sławomir Jerzy_1": 58,
            "NAWROCKI Karol Tadeusz_1": 133,
            "SENYSZYN Joanna_1": 2,
            "STANOWSKI Krzysztof Jakub_1": 4,
            "TRZASKOWSKI Rafał Kazimierz_1": 75,
            "WOCH Marek Marian_1": 0,
            "ZANDBERG Adrian Tadeusz_1": 8
        },
        "second_round": {
            "eligible_voters_2": 592,
            "issued_2": 377,
            "turnout_2": 63.68,
            "NAWROCKI Karol Tadeusz_2": 243,
            "TRZASKOWSKI Rafał Kazimierz_2": 132
        },
        "calculations": {
            "issued_scale": 1.149390243902439,
            "change_TRZASKOWSKI Rafał Kazimierz": 0.76,
            "change_NAWROCKI Karol Tadeusz": 0.8271,
            "expected_nawrocki": 249.19,
            "expected_trzaskowski": 120.91,
            "delta_nawrocki": -6.193551829268301,
            "delta_trzaskowski": 11.08989329268293,
            "diff_pct_nawrocki": -0.0249,
            "delta_from_median_change": 0.0083,
            "delta_from_median_difference": -0.0291,
            "alert_index": 0.0248,
            "change_TRZASKOWSKI Rafał Kazimierz_pct": 76,
            "change_NAWROCKI Karol Tadeusz_pct": 82.71,
            "diff_pct_nawrocki_pct": -2.49,
            "delta_from_median_change_pct": 0.83,
            "delta_from_median_difference_pct": -2.91,
            "alert_index_pct": 2.48
        },
        "alert_index_pct": 0.0248,
        "alert_index": 0.0248
    },
    {
        "commission": {
            "Nr komisji": "27",
            "Gmina": "gm. Grodków",
            "Teryt Gminy": "160103",
            "Powiat": "brzeski",
            "Teryt Powiatu": "160100",
            "Województwo": "opolskie",
            "Siedziba": "Świetlica Wiejska w Lubczy, Lubcz 33, 49-200 Grodków",
            "Typ obwodu": "stały",
            "Typ obszaru": "wieś",
            "id": "8599643a001ade508228e7c12a1d4db8"
        },
        "turnout": {
            "first": "64.71% (110 z 170)",
            "second": "71.6% (121 z 169)",
            "scale": 1.1064750424972956
        },
        "first_round": {
            "eligible_voters_1": 170,
            "issued_1": 110,
            "turnout_1": 64.71,
            "BARTOSZEWICZ Artur_1": 0,
            "BIEJAT Magdalena Agnieszka_1": 3,
            "BRAUN Grzegorz Michał_1": 5,
            "HOŁOWNIA Szymon Franciszek_1": 4,
            "JAKUBIAK Marek_1": 2,
            "MACIAK Maciej_1": 0,
            "MENTZEN Sławomir Jerzy_1": 28,
            "NAWROCKI Karol Tadeusz_1": 25,
            "SENYSZYN Joanna_1": 2,
            "STANOWSKI Krzysztof Jakub_1": 1,
            "TRZASKOWSKI Rafał Kazimierz_1": 36,
            "WOCH Marek Marian_1": 0,
            "ZANDBERG Adrian Tadeusz_1": 4
        },
        "second_round": {
            "eligible_voters_2": 169,
            "issued_2": 121,
            "turnout_2": 71.6,
            "NAWROCKI Karol Tadeusz_2": 61,
            "TRZASKOWSKI Rafał Kazimierz_2": 59
        },
        "calculations": {
            "issued_scale": 1.1,
            "change_TRZASKOWSKI Rafał Kazimierz": 0.6389,
            "change_NAWROCKI Karol Tadeusz": 1.44,
            "expected_nawrocki": 62.55,
            "expected_trzaskowski": 56.25,
            "delta_nawrocki": -1.5482000000000014,
            "delta_trzaskowski": 2.748199999999997,
            "diff_pct_nawrocki": -0.0248,
            "delta_from_median_change": 0.6212,
            "delta_from_median_difference": -0.029,
            "alert_index": 0.0248,
            "change_TRZASKOWSKI Rafał Kazimierz_pct": 63.89,
            "change_NAWROCKI Karol Tadeusz_pct": 144,
            "diff_pct_nawrocki_pct": -2.48,
            "delta_from_median_change_pct": 62.12,
            "delta_from_median_difference_pct": -2.9,
            "alert_index_pct": 2.48
        },
        "alert_index_pct": 0.0248,
        "alert_index": 0.0248
    },
    {
        "commission": {
            "Nr komisji": "2",
            "Gmina": "gm. Turawa",
            "Teryt Gminy": "160913",
            "Powiat": "opolski",
            "Teryt Powiatu": "160900",
            "Województwo": "opolskie",
            "Siedziba": "Szkoła Podstawowa, Kadłub Turawski ul. Główna 12, 46-046 Ligota Turawska",
            "Typ obwodu": "stały",
            "Typ obszaru": "wieś",
            "id": "f44f82404df70afbc69a28dfe9829189"
        },
        "turnout": {
            "first": "44.55% (180 z 404)",
            "second": "44.83% (182 z 406)",
            "scale": 1.0062850729517396
        },
        "first_round": {
            "eligible_voters_1": 404,
            "issued_1": 180,
            "turnout_1": 44.55,
            "BARTOSZEWICZ Artur_1": 3,
            "BIEJAT Magdalena Agnieszka_1": 2,
            "BRAUN Grzegorz Michał_1": 16,
            "HOŁOWNIA Szymon Franciszek_1": 9,
            "JAKUBIAK Marek_1": 2,
            "MACIAK Maciej_1": 2,
            "MENTZEN Sławomir Jerzy_1": 37,
            "NAWROCKI Karol Tadeusz_1": 40,
            "SENYSZYN Joanna_1": 1,
            "STANOWSKI Krzysztof Jakub_1": 3,
            "TRZASKOWSKI Rafał Kazimierz_1": 59,
            "WOCH Marek Marian_1": 0,
            "ZANDBERG Adrian Tadeusz_1": 5
        },
        "second_round": {
            "eligible_voters_2": 406,
            "issued_2": 182,
            "turnout_2": 44.83,
            "NAWROCKI Karol Tadeusz_2": 95,
            "TRZASKOWSKI Rafał Kazimierz_2": 85
        },
        "calculations": {
            "issued_scale": 1.011111111111111,
            "change_TRZASKOWSKI Rafał Kazimierz": 0.4407,
            "change_NAWROCKI Karol Tadeusz": 1.375,
            "expected_nawrocki": 92.7,
            "expected_trzaskowski": 81.21,
            "delta_nawrocki": 2.301333333333332,
            "delta_trzaskowski": 3.7875555555555707,
            "diff_pct_nawrocki": 0.0248,
            "delta_from_median_change": 0.5562,
            "delta_from_median_difference": 0.0206,
            "alert_index": 0.0248,
            "change_TRZASKOWSKI Rafał Kazimierz_pct": 44.07,
            "change_NAWROCKI Karol Tadeusz_pct": 137.5,
            "diff_pct_nawrocki_pct": 2.48,
            "delta_from_median_change_pct": 55.62,
            "delta_from_median_difference_pct": 2.06,
            "alert_index_pct": 2.48
        },
        "alert_index_pct": 0.0248,
        "alert_index": 0.0248
    },
    {
        "commission": {
            "Nr komisji": "11",
            "Gmina": "gm. Rymanów",
            "Teryt Gminy": "180708",
            "Powiat": "krośnieński",
            "Teryt Powiatu": "180700",
            "Województwo": "podkarpackie",
            "Siedziba": "Zespół Szkół Publicznych w Posadzie Górnej, Posada Górna ul. 3 Maja 164, 38-481 Rymanów-Zdrój",
            "Typ obwodu": "stały",
            "Typ obszaru": "wieś",
            "id": "f7383b508f87caec4e46a47404d1d4f5"
        },
        "turnout": {
            "first": "69.82% (856 z 1226)",
            "second": "73.71% (886 z 1202)",
            "scale": 1.0557146949298195
        },
        "first_round": {
            "eligible_voters_1": 1226,
            "issued_1": 856,
            "turnout_1": 69.82,
            "BARTOSZEWICZ Artur_1": 2,
            "BIEJAT Magdalena Agnieszka_1": 16,
            "BRAUN Grzegorz Michał_1": 70,
            "HOŁOWNIA Szymon Franciszek_1": 44,
            "JAKUBIAK Marek_1": 4,
            "MACIAK Maciej_1": 0,
            "MENTZEN Sławomir Jerzy_1": 158,
            "NAWROCKI Karol Tadeusz_1": 388,
            "SENYSZYN Joanna_1": 11,
            "STANOWSKI Krzysztof Jakub_1": 7,
            "TRZASKOWSKI Rafał Kazimierz_1": 113,
            "WOCH Marek Marian_1": 0,
            "ZANDBERG Adrian Tadeusz_1": 33
        },
        "second_round": {
            "eligible_voters_2": 1202,
            "issued_2": 886,
            "turnout_2": 73.71,
            "NAWROCKI Karol Tadeusz_2": 646,
            "TRZASKOWSKI Rafał Kazimierz_2": 229
        },
        "calculations": {
            "issued_scale": 1.0350467289719627,
            "change_TRZASKOWSKI Rafał Kazimierz": 1.0265,
            "change_NAWROCKI Karol Tadeusz": 0.6649,
            "expected_nawrocki": 630.35,
            "expected_trzaskowski": 239.08,
            "delta_nawrocki": 15.645156542056043,
            "delta_trzaskowski": -10.08440887850469,
            "diff_pct_nawrocki": 0.0248,
            "delta_from_median_change": -0.1539,
            "delta_from_median_difference": 0.0206,
            "alert_index": 0.0248,
            "change_TRZASKOWSKI Rafał Kazimierz_pct": 102.65,
            "change_NAWROCKI Karol Tadeusz_pct": 66.49,
            "diff_pct_nawrocki_pct": 2.48,
            "delta_from_median_change_pct": -15.39,
            "delta_from_median_difference_pct": 2.06,
            "alert_index_pct": 2.48
        },
        "alert_index_pct": 0.0248,
        "alert_index": 0.0248
    },
    {
        "commission": {
            "Nr komisji": "1",
            "Gmina": "gm. Drohiczyn",
            "Teryt Gminy": "201002",
            "Powiat": "siemiatycki",
            "Teryt Powiatu": "201000",
            "Województwo": "podlaskie",
            "Siedziba": "Drohiczyn, Miejsko Gminny Ośrodek Kultury w Drohiczynie, ul. Józefa Ignacego Kraszewskiego 13, 17-312 Drohiczyn",
            "Typ obwodu": "stały",
            "Typ obszaru": "miasto",
            "id": "4505b1d18d9b92989255c9deb7747b1b"
        },
        "turnout": {
            "first": "60.92% (909 z 1492)",
            "second": "65.21% (969 z 1486)",
            "scale": 1.070420223243598
        },
        "first_round": {
            "eligible_voters_1": 1492,
            "issued_1": 909,
            "turnout_1": 60.92,
            "BARTOSZEWICZ Artur_1": 5,
            "BIEJAT Magdalena Agnieszka_1": 29,
            "BRAUN Grzegorz Michał_1": 75,
            "HOŁOWNIA Szymon Franciszek_1": 41,
            "JAKUBIAK Marek_1": 4,
            "MACIAK Maciej_1": 2,
            "MENTZEN Sławomir Jerzy_1": 106,
            "NAWROCKI Karol Tadeusz_1": 395,
            "SENYSZYN Joanna_1": 11,
            "STANOWSKI Krzysztof Jakub_1": 8,
            "TRZASKOWSKI Rafał Kazimierz_1": 217,
            "WOCH Marek Marian_1": 0,
            "ZANDBERG Adrian Tadeusz_1": 13
        },
        "second_round": {
            "eligible_voters_2": 1486,
            "issued_2": 969,
            "turnout_2": 65.21,
            "NAWROCKI Karol Tadeusz_2": 627,
            "TRZASKOWSKI Rafał Kazimierz_2": 336
        },
        "calculations": {
            "issued_scale": 1.066006600660066,
            "change_TRZASKOWSKI Rafał Kazimierz": 0.5484,
            "change_NAWROCKI Karol Tadeusz": 0.5873,
            "expected_nawrocki": 611.83,
            "expected_trzaskowski": 342.24,
            "delta_nawrocki": 15.168709570957162,
            "delta_trzaskowski": -6.244617161716121,
            "diff_pct_nawrocki": 0.0248,
            "delta_from_median_change": -0.2315,
            "delta_from_median_difference": 0.0206,
            "alert_index": 0.0248,
            "change_TRZASKOWSKI Rafał Kazimierz_pct": 54.84,
            "change_NAWROCKI Karol Tadeusz_pct": 58.73,
            "diff_pct_nawrocki_pct": 2.48,
            "delta_from_median_change_pct": -23.15,
            "delta_from_median_difference_pct": 2.06,
            "alert_index_pct": 2.48
        },
        "alert_index_pct": 0.0248,
        "alert_index": 0.0248
    },
    {
        "commission": {
            "Nr komisji": "8",
            "Gmina": "gm. Bytów",
            "Teryt Gminy": "220102",
            "Powiat": "bytowski",
            "Teryt Powiatu": "220100",
            "Województwo": "pomorskie",
            "Siedziba": "Zespół Szkół Ekonomiczno-Usługowych, ul. Hieronima Derdowskiego 3, 77-100 Bytów",
            "Typ obwodu": "stały",
            "Typ obszaru": "miasto",
            "id": "4bf314aa98640819e3d8c1f8a02c7d72"
        },
        "turnout": {
            "first": "64.52% (411 z 637)",
            "second": "68.56% (434 z 633)",
            "scale": 1.0626162430254187
        },
        "first_round": {
            "eligible_voters_1": 637,
            "issued_1": 411,
            "turnout_1": 64.52,
            "BARTOSZEWICZ Artur_1": 0,
            "BIEJAT Magdalena Agnieszka_1": 7,
            "BRAUN Grzegorz Michał_1": 29,
            "HOŁOWNIA Szymon Franciszek_1": 42,
            "JAKUBIAK Marek_1": 4,
            "MACIAK Maciej_1": 0,
            "MENTZEN Sławomir Jerzy_1": 69,
            "NAWROCKI Karol Tadeusz_1": 107,
            "SENYSZYN Joanna_1": 1,
            "STANOWSKI Krzysztof Jakub_1": 5,
            "TRZASKOWSKI Rafał Kazimierz_1": 132,
            "WOCH Marek Marian_1": 0,
            "ZANDBERG Adrian Tadeusz_1": 15
        },
        "second_round": {
            "eligible_voters_2": 633,
            "issued_2": 434,
            "turnout_2": 68.56,
            "NAWROCKI Karol Tadeusz_2": 213,
            "TRZASKOWSKI Rafał Kazimierz_2": 217
        },
        "calculations": {
            "issued_scale": 1.0559610705596107,
            "change_TRZASKOWSKI Rafał Kazimierz": 0.6439,
            "change_NAWROCKI Karol Tadeusz": 0.9907,
            "expected_nawrocki": 218.42,
            "expected_trzaskowski": 211.35,
            "delta_nawrocki": -5.421323600973238,
            "delta_trzaskowski": 5.645167883211684,
            "diff_pct_nawrocki": -0.0248,
            "delta_from_median_change": 0.1719,
            "delta_from_median_difference": -0.029,
            "alert_index": 0.0248,
            "change_TRZASKOWSKI Rafał Kazimierz_pct": 64.39,
            "change_NAWROCKI Karol Tadeusz_pct": 99.07,
            "diff_pct_nawrocki_pct": -2.48,
            "delta_from_median_change_pct": 17.19,
            "delta_from_median_difference_pct": -2.9,
            "alert_index_pct": 2.48
        },
        "alert_index_pct": 0.0248,
        "alert_index": 0.0248
    },
    {
        "commission": {
            "Nr komisji": "4",
            "Gmina": "gm. Sztum",
            "Teryt Gminy": "221605",
            "Powiat": "sztumski",
            "Teryt Powiatu": "221600",
            "Województwo": "pomorskie",
            "Siedziba": "Szkoła Podstawowa w Nowej Wsi, Nowa Wieś 60, 82-400 Sztum",
            "Typ obwodu": "stały",
            "Typ obszaru": "wieś",
            "id": "7ec2b5d157499da75d2326017d6b9ac0"
        },
        "turnout": {
            "first": "55.25% (363 z 657)",
            "second": "58.37% (380 z 651)",
            "scale": 1.056470588235294
        },
        "first_round": {
            "eligible_voters_1": 657,
            "issued_1": 363,
            "turnout_1": 55.25,
            "BARTOSZEWICZ Artur_1": 2,
            "BIEJAT Magdalena Agnieszka_1": 21,
            "BRAUN Grzegorz Michał_1": 29,
            "HOŁOWNIA Szymon Franciszek_1": 13,
            "JAKUBIAK Marek_1": 2,
            "MACIAK Maciej_1": 1,
            "MENTZEN Sławomir Jerzy_1": 74,
            "NAWROCKI Karol Tadeusz_1": 104,
            "SENYSZYN Joanna_1": 3,
            "STANOWSKI Krzysztof Jakub_1": 5,
            "TRZASKOWSKI Rafał Kazimierz_1": 99,
            "WOCH Marek Marian_1": 0,
            "ZANDBERG Adrian Tadeusz_1": 9
        },
        "second_round": {
            "eligible_voters_2": 651,
            "issued_2": 380,
            "turnout_2": 58.37,
            "NAWROCKI Karol Tadeusz_2": 209,
            "TRZASKOWSKI Rafał Kazimierz_2": 169
        },
        "calculations": {
            "issued_scale": 1.046831955922865,
            "change_TRZASKOWSKI Rafał Kazimierz": 0.7071,
            "change_NAWROCKI Karol Tadeusz": 1.0096,
            "expected_nawrocki": 214.31,
            "expected_trzaskowski": 159.41,
            "delta_nawrocki": -5.305344352617084,
            "delta_trzaskowski": 9.586336088154269,
            "diff_pct_nawrocki": -0.0248,
            "delta_from_median_change": 0.1908,
            "delta_from_median_difference": -0.029,
            "alert_index": 0.0248,
            "change_TRZASKOWSKI Rafał Kazimierz_pct": 70.71,
            "change_NAWROCKI Karol Tadeusz_pct": 100.96,
            "diff_pct_nawrocki_pct": -2.48,
            "delta_from_median_change_pct": 19.08,
            "delta_from_median_difference_pct": -2.9,
            "alert_index_pct": 2.48
        },
        "alert_index_pct": 0.0248,
        "alert_index": 0.0248
    },
    {
        "commission": {
            "Nr komisji": "6",
            "Gmina": "gm. Łodygowice",
            "Teryt Gminy": "241708",
            "Powiat": "żywiecki",
            "Teryt Powiatu": "241700",
            "Województwo": "śląskie",
            "Siedziba": "Zespół Szkolno-Przedszkolny, ul. Kościuszki 120, 34-326 Pietrzykowice",
            "Typ obwodu": "stały",
            "Typ obszaru": "wieś",
            "id": "bf11aa5175d573f8352822efc8ab64c1"
        },
        "turnout": {
            "first": "70.08% (1164 z 1661)",
            "second": "71.52% (1175 z 1643)",
            "scale": 1.0205479452054793
        },
        "first_round": {
            "eligible_voters_1": 1661,
            "issued_1": 1164,
            "turnout_1": 70.08,
            "BARTOSZEWICZ Artur_1": 1,
            "BIEJAT Magdalena Agnieszka_1": 43,
            "BRAUN Grzegorz Michał_1": 92,
            "HOŁOWNIA Szymon Franciszek_1": 68,
            "JAKUBIAK Marek_1": 9,
            "MACIAK Maciej_1": 4,
            "MENTZEN Sławomir Jerzy_1": 217,
            "NAWROCKI Karol Tadeusz_1": 403,
            "SENYSZYN Joanna_1": 8,
            "STANOWSKI Krzysztof Jakub_1": 16,
            "TRZASKOWSKI Rafał Kazimierz_1": 247,
            "WOCH Marek Marian_1": 1,
            "ZANDBERG Adrian Tadeusz_1": 45
        },
        "second_round": {
            "eligible_voters_2": 1643,
            "issued_2": 1175,
            "turnout_2": 71.52,
            "NAWROCKI Karol Tadeusz_2": 734,
            "TRZASKOWSKI Rafał Kazimierz_2": 433
        },
        "calculations": {
            "issued_scale": 1.0094501718213058,
            "change_TRZASKOWSKI Rafał Kazimierz": 0.753,
            "change_NAWROCKI Karol Tadeusz": 0.8213,
            "expected_nawrocki": 716.22,
            "expected_trzaskowski": 433.54,
            "delta_nawrocki": 17.77693298969075,
            "delta_trzaskowski": -0.540678694158089,
            "diff_pct_nawrocki": 0.0248,
            "delta_from_median_change": 0.0025,
            "delta_from_median_difference": 0.0206,
            "alert_index": 0.0248,
            "change_TRZASKOWSKI Rafał Kazimierz_pct": 75.3,
            "change_NAWROCKI Karol Tadeusz_pct": 82.13,
            "diff_pct_nawrocki_pct": 2.48,
            "delta_from_median_change_pct": 0.25,
            "delta_from_median_difference_pct": 2.06,
            "alert_index_pct": 2.48
        },
        "alert_index_pct": 0.0248,
        "alert_index": 0.0248
    },
    {
        "commission": {
            "Nr komisji": "14",
            "Gmina": "m. Mysłowice",
            "Teryt Gminy": "247001",
            "Powiat": "Mysłowice",
            "Teryt Powiatu": "247000",
            "Województwo": "śląskie",
            "Siedziba": "Szkoła Podstawowa Nr 4 z Oddziałami Dwujęzycznymi, ul. Wielka Skotnica 84a, 41-400 Mysłowice",
            "Typ obwodu": "stały",
            "Typ obszaru": "miasto",
            "id": "596c508c0c7422055a872b55286d42d9"
        },
        "turnout": {
            "first": "68.12% (1327 z 1948)",
            "second": "72.24% (1392 z 1927)",
            "scale": 1.0604815032295947
        },
        "first_round": {
            "eligible_voters_1": 1948,
            "issued_1": 1327,
            "turnout_1": 68.12,
            "BARTOSZEWICZ Artur_1": 4,
            "BIEJAT Magdalena Agnieszka_1": 74,
            "BRAUN Grzegorz Michał_1": 70,
            "HOŁOWNIA Szymon Franciszek_1": 81,
            "JAKUBIAK Marek_1": 8,
            "MACIAK Maciej_1": 4,
            "MENTZEN Sławomir Jerzy_1": 202,
            "NAWROCKI Karol Tadeusz_1": 344,
            "SENYSZYN Joanna_1": 18,
            "STANOWSKI Krzysztof Jakub_1": 23,
            "TRZASKOWSKI Rafał Kazimierz_1": 432,
            "WOCH Marek Marian_1": 0,
            "ZANDBERG Adrian Tadeusz_1": 57
        },
        "second_round": {
            "eligible_voters_2": 1927,
            "issued_2": 1392,
            "turnout_2": 72.24,
            "NAWROCKI Karol Tadeusz_2": 646,
            "TRZASKOWSKI Rafał Kazimierz_2": 731
        },
        "calculations": {
            "issued_scale": 1.0489826676714393,
            "change_TRZASKOWSKI Rafał Kazimierz": 0.6921,
            "change_NAWROCKI Karol Tadeusz": 0.8779,
            "expected_nawrocki": 662.4,
            "expected_trzaskowski": 702.33,
            "delta_nawrocki": -16.39688922381299,
            "delta_trzaskowski": 28.67043858327054,
            "diff_pct_nawrocki": -0.0248,
            "delta_from_median_change": 0.0591,
            "delta_from_median_difference": -0.029,
            "alert_index": 0.0248,
            "change_TRZASKOWSKI Rafał Kazimierz_pct": 69.21,
            "change_NAWROCKI Karol Tadeusz_pct": 87.79,
            "diff_pct_nawrocki_pct": -2.48,
            "delta_from_median_change_pct": 5.91,
            "delta_from_median_difference_pct": -2.9,
            "alert_index_pct": 2.48
        },
        "alert_index_pct": 0.0248,
        "alert_index": 0.0248
    }
]